Workbook
Name condition_1085B4A664DA38CA9CAB09C9B0B2E251: 'Conditions List'!$C$7:$C$7
Name condition_146DD677425832B1B256FDC2A6A4A1EA: 'Conditions List'!$C$24:$O$24
Name condition_1FDC4E4E7716327980BE0EB5F85DDAB1: 'Conditions List'!$C$13:$D$13
Name condition_2926A45167D03778A2AE22BD860CDE82: 'Conditions List'!$C$10:$C$10
Name condition_308E72ECF4B933A6A3C645A8467BC71E: 'Conditions List'!$C$3:$G$3
Name condition_3710C0A819223E3487D01309378226DC: 'Conditions List'!$C$31:$E$31
Name condition_457FDBB5A67735DAB66C4713D23E75A2: 'Conditions List'!$C$4:$C$4
Name condition_5C293928C78C306A9965E2888BA342B3: 'Conditions List'!$C$9:$C$9
Name condition_6175D3D1E7333AEDB59353B9CA9482FD: 'Conditions List'!$C$22:$O$22
Name condition_66EB70B5C5A43B5B8FF26B31B1817A2C: 'Conditions List'!$C$29:$X$29
Name condition_67B14A71EFCC3F83990EA6A2D66BFEA2: 'Conditions List'!$C$12:$C$12
Name condition_680D3B7617DD3F0ABAA8270BBDCAD9BB: 'Conditions List'!$C$30:$X$30
Name condition_681821EFDCEC3C3B93CC6D793E12D966: 'Conditions List'!$C$25:$O$25
Name condition_7FDFA689F55D37C8BCE13934576805D0: 'Conditions List'!$C$5:$F$5
Name condition_821ADFECFB703A71867851F81F19CF78: 'Conditions List'!$C$21:$O$21
Name condition_851AB4D926583A659171AB36316BE900: 'Conditions List'!$C$15:$O$15
Name condition_8617D3E9125F33BC88F0F75538411BAF: 'Conditions List'!$C$8:$C$8
Name condition_89D3B1E0A9DA3555B19AC4B84605A88B: 'Conditions List'!$C$1:$C$1
Name condition_8E5E53BB8B9535AFA1C23BCA9C5DD874: 'Conditions List'!$C$20:$O$20
Name condition_9FBC0C23B75D3104B2C40A8BEBCAAFB9: 'Conditions List'!$C$19:$O$19
Name condition_A8D0A7B1410F39BAB2C826C292BDD6AC: 'Conditions List'!$C$26:$O$26
Name condition_BE605DFE9D193FD9A5D762C182A4D048: 'Conditions List'!$C$11:$C$11
Name condition_C0EAB11EDA263845BE4CA17346F5CF86: 'Conditions List'!$C$27:$O$27
Name condition_C196059A8C3D3CAC96A0D72243A2599D: 'Conditions List'!$C$23:$O$23
Name condition_C921CBEA72BB3E85B3BE9EB274D77809: 'Conditions List'!$C$28:$C$28
Name condition_CE1DE48E77B733A4A7A298C30F08B784: 'Conditions List'!$C$6:$C$6
Name condition_D45499349AFB3761AE10B8529FEA03C2: 'Conditions List'!$C$16:$O$16
Name condition_DF5CC8DF05DF3C579F7588A18BC94C31: 'Conditions List'!$C$18:$O$18
Name condition_E3429B7064A735D8AE16EA22E3B72AE9: 'Conditions List'!$C$14:$D$14
Name condition_E36409CE568836BAA4F1A31911103C9D: 'Conditions List'!$C$17:$O$17
Name condition_E91D7D3AED243B3C9270F77B3B13D394: 'Conditions List'!$C$2:$D$2
Name t_012109DDB92E37C782942343C3FAA646: 'Dropdown Lists'!$C$54:$E$54
Name t_01BA699F340E3B1C80CC2D963BF4E23C: 'Dropdown Lists'!$C$22:$BY$22
Name t_041CCA92EE77300983BA260D5471D2F6: 'Dropdown Lists'!$C$49:$I$49
Name t_0BBD854D7BD33808B617FC1FB91FF644: 'Dropdown Lists'!$C$56:$I$56
Name t_0F3F86297DFD333C9666B531B0353B3C: 'Dropdown Lists'!$C$35:$D$35
Name t_102B0F8B23393DE98AFB27DE3D742D48: 'Dropdown Lists'!$C$15:$F$15
Name t_12264466A77D3B36AC2DAA034A1A5FE2: 'Dropdown Lists'!$C$20:$G$20
Name t_1636BD1CFBD53CA59961F2B345D4FEEB: 'Dropdown Lists'!$C$55:$D$55
Name t_1AE68FAE4C233AF2AAD93B3EC17512F8: 'Dropdown Lists'!$C$42:$D$42
Name t_1CFBAFB02535396A90C8042DFA8BC3FD: 'Dropdown Lists'!$C$47:$C$47
Name t_1DEE4A266E48377DA726E10015B5D56F: 'Dropdown Lists'!$C$65:$HU$65
Name t_210AC56516C831C3B975426026564B85: 'Dropdown Lists'!$C$4:$H$4
Name t_241370342FE93115B86141B16F0D66B3: 'Dropdown Lists'!$C$46:$F$46
Name t_24E9F6E5671238AEB940988128184600: 'Dropdown Lists'!$C$18:$AV$18
Name t_275F523CC3DA36BF82F6D13DA3C4DE73: 'Dropdown Lists'!$C$51:$G$51
Name t_3210EDB3F0FF3AABAF0449B028E64379: 'Dropdown Lists'!$C$30:$J$30
Name t_358C61997BEA39239CE0596AA5F8E1FD: 'Dropdown Lists'!$C$52:$I$52
Name t_35F193C6A7E13FE09ED9BAE2922D841A: 'Dropdown Lists'!$C$59:$G$59
Name t_395E9262634839C383597E24E1E36964: 'Dropdown Lists'!$C$68:$AHP$68
Name t_3F8AAC6653D43B55B905228704037B79: 'Dropdown Lists'!$C$57:$I$57
Name t_4BDCEE54E14C361091E3B7E7BC6BFA58: 'Dropdown Lists'!$C$8:$F$8
Name t_4D0B0322FE473E23B6C86F1C3A06BA2B: 'Dropdown Lists'!$C$25:$J$25
Name t_4D36BB0BF9A633DDA10597E97D2DE70D: 'Dropdown Lists'!$C$12:$G$12
Name t_4E6356A2F95E3E55B9B8EF4AFCA2B468: 'Dropdown Lists'!$C$63:$F$63
Name t_4E8EB62C344D3136894C37789B634AC8: 'Dropdown Lists'!$C$9:$K$9
Name t_4FCF4D5E513C3C149F22DA945CD3A4F9: 'Dropdown Lists'!$C$24:$I$24
Name t_548CA8DB852B3D74B0E67F20F3C16269: 'Dropdown Lists'!$C$29:$J$29
Name t_5848D61FB8923C738935B53104584AF7: 'Dropdown Lists'!$C$37:$C$37
Name t_59D4DF059C473EBE9972B0D6D3C6BFD5: 'Dropdown Lists'!$C$16:$E$16

Sheet Template
A1: Processing Results | E1: Product Identity | T1: Product Description | DS1: Product Detail | EQ1: Sale Property (At Least One, At Most Two) | FE1: Variations | GI1: Offer | GM1: Qualifications
A2: Goods Id | B2: Sku Id | C2: Status | D2: Details | E2: Category | F2: Category Name | G2: Product type | H2: Customization processing technique | I2: Primary technique | J2: Secondary technique | K2: Secondary technique | L2: Product Name | M2: Contribution Goods | N2: Contribution SKU | O2: Update or Add | P2: Goods Id | Q2: Sku Id | R2: Brand | S2: Trademark | T2: Product Description | U2: Bullet Point | V2: Bullet Point | W2: Bullet Point | X2: Bullet Point | Y2: Bullet Point | Z2: Bullet Point | AA2: Detail Images URL | AB2: Detail Images URL | AC2: Detail Images URL | AD2: Detail Images URL | AE2: Detail Images URL | AF2: Detail Images URL | AG2: Detail Images URL | AH2: Detail Images URL | AI2: Detail Images URL | AJ2: Detail Images URL | AK2: Detail Images URL | AL2: Detail Images URL | AM2: Detail Images URL | AN2: Detail Images URL | AO2: Detail Images URL | AP2: Detail Images URL | AQ2: Detail Images URL | AR2: Detail Images URL | AS2: Detail Images URL | AT2: Detail Images URL | AU2: Detail Images URL | AV2: Detail Images URL | AW2: Detail Images URL | AX2: Detail Images URL | AY2: Detail Images URL | AZ2: Detail Images URL | BA2: Detail Images URL | BB2: Detail Images URL | BC2: Detail Images URL | BD2: Detail Images URL | BE2: Detail Images URL | BF2: Detail Images URL | BG2: Detail Images URL | BH2: Detail Images URL | BI2: Detail Images URL | BJ2: Detail Images URL | BK2: Detail Images URL | BL2: Detail Images URL | BM2: Detail Images URL | BN2: Detail Images URL | BO2: Detail Images URL | BP2: Detail Images URL | BQ2: Detail Images URL | BR2: Detail Images URL | BS2: Detail Images URL | BT2: Detail Images URL | BU2: Detail Images URL | BV2: Detail Images URL | BW2: Detail Images URL | BX2: Detail Images URL | BY2: Detail Images URL | BZ2: Detail Images URL | CA2: Detail Images URL | CB2: Detail Images URL | CC2: Detail Images URL | CD2: Detail Images URL | CE2: Detail Images URL | CF2: Detail Images URL | CG2: Detail Images URL | CH2: Detail Images URL | CI2: Detail Images URL | CJ2: Detail Images URL | CK2: Detail Images URL | CL2: Detail Images URL | CM2: Detail Images URL | CN2: Detail Images URL | CO2: Detail Images URL | CP2: Detail Images URL | CQ2: Detail Images URL | CR2: Detail Images URL | CS2: Detail Images URL | CT2: Detail Images URL | CU2: Detail Images URL | CV2: Detail Images URL | CW2: Detail Images URL | CX2: Detail Images URL | CY2: Detail Images URL | CZ2: Detail Images URL | DA2: Detail Images URL | DB2: Detail Images URL | DC2: Detail Images URL | DD2: Detail Images URL | DE2: Detail Images URL | DF2: Detail Images URL | DG2: Detail Images URL | DH2: Detail Images URL | DI2: Detail Images URL | DJ2: Detail Images URL | DK2: Detail Images URL | DL2: Detail Images URL | DM2: Detail Images URL | DN2: Detail Images URL | DO2: Detail Images URL | DP2: Detail Images URL | DQ2: Detail Images URL | DR2: Detail Video URL | DS2: 19 - Style | DT2: 423 - Holidays | DU2: 423 - Holidays | DV2: 423 - Holidays | DW2: 423 - Holidays | DX2: 423 - Holidays | DY2: 127 - Mounting Type | DZ2: 121 - Material | EA2: 130 - Theme | EB2: 2232 - Whether There Are Feathers | EC2: 2233 - Feather Material | ED2: 1561 - Power Supply | EE2: 1132 - Operating Voltage | EF2: 1562 - Battery Quantity | EG2: 137 - Battery Type | EH2: 1563 - Battery Included or Not | EI2: 1485 - Plug Type | EJ2: 2147 - Rechargeable Battery | EK2: 2154 - Solar Battery Type | EL2: 111 - Batteries Included | EM2: 2028 - Battery Capacity (mAh) - value | EN2: 2028 - Battery Capacity (mAh) - unit | EO2: 3673 - Language Type | EP2: 7644 - Does It Contain Real Plants? | EQ2: Variation Theme | ER2: Color | ES2: Size | ET2: Style | EU2: Material | EV2: Flavors | EW2: Applicable People | EX2: Capacity | EY2: Composition | EZ2: Weight | FA2: Items | FB2: Quantity | FC2: Model | FD2: Hair Length | FE2: SKU Images URL | FF2: SKU Images URL | FG2: SKU Images URL | FH2: SKU Images URL | FI2: SKU Images URL | FJ2: SKU Images URL | FK2: SKU Images URL | FL2: SKU Images URL | FM2: SKU Images URL | FN2: SKU Images URL | FO2: Dimensions | FP2: Quantity | FQ2: Base Price - USD | FR2: Reference Link | FS2: List Price - USD | FT2: Weight - lb | FU2: Length - in | FV2: Width - in | FW2: Height - in | FX2: SKU type | FY2: Individually packed | FZ2: Total packaging quantity | GA2: Packaging unit | GB2: Total item quantity | GC2: Item unit | GD2: Net content | GE2: Total net content | GF2: Net content unit | GG2: External Product ID Type | GH2: External Product ID | GI2: Shipping Template | GJ2: Handling Time | GK2: Import Designation | GL2: Fulfillment Channel | GM2: Country/Region of Origin | GN2: Province of Origin | GO2: SKU Packaging Information (with visible label) | GP2: SKU Packaging Information (with visible label) | GQ2: SKU Packaging Information (with visible label) | GR2: SKU Packaging Information (with visible label) | GS2: SKU Packaging Information (with visible label) | GT2: SKU Packaging Information (with visible label) | GU2: SKU Packaging Information (with visible label) | GV2: SKU Packaging Information (with visible label) | GW2: SKU Packaging Information (with visible label) | GX2: SKU Packaging Information (with visible label) | GY2: SKU Packaging Information (with visible label) | GZ2: SKU Packaging Information (with visible label) | HA2: SKU Packaging Information (with visible label) | HB2: SKU Packaging Information (with visible label) | HC2: SKU Packaging Information (with visible label) | HD2: SKU Packaging Information (with visible label) | HE2: SKU Packaging Information (with visible label) | HF2: SKU Packaging Information (with visible label) | HG2: SKU Packaging Information (with visible label) | HH2: SKU Packaging Information (with visible label) | HI2: SKU Packaging Information (with visible label) | HJ2: SKU Packaging Information (with visible label) | HK2: SKU Packaging Information (with visible label) | HL2: SKU Packaging Information (with visible label) | HM2: SKU Packaging Information (with visible label) | HN2: SKU Packaging Information (with visible label) | HO2: SKU Packaging Information (with visible label) | HP2: SKU Packaging Information (with visible label) | HQ2: SKU Packaging Information (with visible label) | HR2: SKU Packaging Information (with visible label) | HS2: SKU Packaging Information (with visible label) | HT2: SKU Packaging Information (with visible label) | HU2: SKU Packaging Information (with visible label) | HV2: SKU Packaging Information (with visible label) | HW2: SKU Packaging Information (with visible label) | HX2: SKU Packaging Information (with visible label) | HY2: SKU Packaging Information (with visible label) | HZ2: SKU Packaging Information (with visible label) | IA2: SKU Packaging Information (with visible label) | IB2: SKU Packaging Information (with visible label) | IC2: SKU Packaging Information (with visible label) | ID2: SKU Packaging Information (with visible label) | IE2: SKU Packaging Information (with visible label) | IF2: SKU Packaging Information (with visible label) | IG2: SKU Packaging Information (with visible label) | IH2: Origin Label & Manufacturer Information | II2: Origin Label & Manufacturer Information | IJ2: Origin Label & Manufacturer Information | IK2: Origin Label & Manufacturer Information | IL2: Origin Label & Manufacturer Information | IM2: Product Guide - English | IN2: California Proposition 65 Warning Type | IO2: California Proposition 65 Chemical Names
A3: Reserved line, prohibit any operation. | B3: Reserved line, prohibit any operation. | C3: Reserved line, prohibit any operation. | D3: Reserved line, prohibit any operation. | E3: eyJ0ZW1wbGF0ZV9pZCI6NTY0ODQzMzk2ODEwNTI3LCJ0ZW1wbGF0ZV9sYW5ndWFnZSI6ImVuIiwic2l0ZV9pZCI6MTAwLCJ2ZXJzaW9uIjoiMy4wLjAiLCJ0eXBlIjowfQ== | F3: Reserved line, prohibit any operation. | G3: Reserved line, prohibit any operation. | H3: Reserved line, prohibit any operation. | I3: Reserved line, prohibit any operation. | J3: Reserved line, prohibit any operation. | K3: Reserved line, prohibit any operation. | L3: Reserved line, prohibit any operation. | M3: Reserved line, prohibit any operation. | N3: Reserved line, prohibit any operation. | O3: Reserved line, prohibit any operation. | P3: Reserved line, prohibit any operation. | Q3: Reserved line, prohibit any operation. | R3: Reserved line, prohibit any operation. | S3: Reserved line, prohibit any operation. | T3: Reserved line, prohibit any operation. | U3: Reserved line, prohibit any operation. | V3: Reserved line, prohibit any operation. | W3: Reserved line, prohibit any operation. | X3: Reserved line, prohibit any operation. | Y3: Reserved line, prohibit any operation. | Z3: Reserved line, prohibit any operation. | AA3: Reserved line, prohibit any operation. | AB3: Reserved line, prohibit any operation. | AC3: Reserved line, prohibit any operation. | AD3: Reserved line, prohibit any operation. | AE3: Reserved line, prohibit any operation. | AF3: Reserved line, prohibit any operation. | AG3: Reserved line, prohibit any operation. | AH3: Reserved line, prohibit any operation. | AI3: Reserved line, prohibit any operation. | AJ3: Reserved line, prohibit any operation. | AK3: Reserved line, prohibit any operation. | AL3: Reserved line, prohibit any operation. | AM3: Reserved line, prohibit any operation. | AN3: Reserved line, prohibit any operation. | AO3: Reserved line, prohibit any operation. | AP3: Reserved line, prohibit any operation. | AQ3: Reserved line, prohibit any operation. | AR3: Reserved line, prohibit any operation. | AS3: Reserved line, prohibit any operation. | AT3: Reserved line, prohibit any operation. | AU3: Reserved line, prohibit any operation. | AV3: Reserved line, prohibit any operation. | AW3: Reserved line, prohibit any operation. | AX3: Reserved line, prohibit any operation. | AY3: Reserved line, prohibit any operation. | AZ3: Reserved line, prohibit any operation. | BA3: Reserved line, prohibit any operation. | BB3: Reserved line, prohibit any operation. | BC3: Reserved line, prohibit any operation. | BD3: Reserved line, prohibit any operation. | BE3: Reserved line, prohibit any operation. | BF3: Reserved line, prohibit any operation. | BG3: Reserved line, prohibit any operation. | BH3: Reserved line, prohibit any operation. | BI3: Reserved line, prohibit any operation. | BJ3: Reserved line, prohibit any operation. | BK3: Reserved line, prohibit any operation. | BL3: Reserved line, prohibit any operation. | BM3: Reserved line, prohibit any operation. | BN3: Reserved line, prohibit any operation. | BO3: Reserved line, prohibit any operation. | BP3: Reserved line, prohibit any operation. | BQ3: Reserved line, prohibit any operation. | BR3: Reserved line, prohibit any operation. | BS3: Reserved line, prohibit any operation. | BT3: Reserved line, prohibit any operation. | BU3: Reserved line, prohibit any operation. | BV3: Reserved line, prohibit any operation. | BW3: Reserved line, prohibit any operation. | BX3: Reserved line, prohibit any operation. | BY3: Reserved line, prohibit any operation. | BZ3: Reserved line, prohibit any operation. | CA3: Reserved line, prohibit any operation. | CB3: Reserved line, prohibit any operation. | CC3: Reserved line, prohibit any operation. | CD3: Reserved line, prohibit any operation. | CE3: Reserved line, prohibit any operation. | CF3: Reserved line, prohibit any operation. | CG3: Reserved line, prohibit any operation. | CH3: Reserved line, prohibit any operation. | CI3: Reserved line, prohibit any operation. | CJ3: Reserved line, prohibit any operation. | CK3: Reserved line, prohibit any operation. | CL3: Reserved line, prohibit any operation. | CM3: Reserved line, prohibit any operation. | CN3: Reserved line, prohibit any operation. | CO3: Reserved line, prohibit any operation. | CP3: Reserved line, prohibit any operation. | CQ3: Reserved line, prohibit any operation. | CR3: Reserved line, prohibit any operation. | CS3: Reserved line, prohibit any operation. | CT3: Reserved line, prohibit any operation. | CU3: Reserved line, prohibit any operation. | CV3: Reserved line, prohibit any operation.
A4: t_0_Goods Id | B4: t_0_Sku Id | C4: t_0_Status | D4: t_0_Details | E4: t_1_Category | F4: t_1_Category Name | G4: t_1_Product type | H4: t_1_Customization processing technique | I4: t_1_Primary technique | J4: t_1_Secondary technique | K4: t_1_Secondary technique | L4: t_1_Product Name | M4: t_1_Contribution Goods | N4: t_1_Contribution SKU | O4: t_1_Update or Add | P4: t_1_Goods Id | Q4: t_1_Sku Id | R4: t_1_Brand | S4: t_1_Trademark | T4: t_2_Product Description | U4: t_2_Bullet Point | V4: t_2_Bullet Point | W4: t_2_Bullet Point | X4: t_2_Bullet Point | Y4: t_2_Bullet Point | Z4: t_2_Bullet Point | AA4: t_2_Detail Images URL | AB4: t_2_Detail Images URL | AC4: t_2_Detail Images URL | AD4: t_2_Detail Images URL | AE4: t_2_Detail Images URL | AF4: t_2_Detail Images URL | AG4: t_2_Detail Images URL | AH4: t_2_Detail Images URL | AI4: t_2_Detail Images URL | AJ4: t_2_Detail Images URL | AK4: t_2_Detail Images URL | AL4: t_2_Detail Images URL | AM4: t_2_Detail Images URL | AN4: t_2_Detail Images URL | AO4: t_2_Detail Images URL | AP4: t_2_Detail Images URL | AQ4: t_2_Detail Images URL | AR4: t_2_Detail Images URL | AS4: t_2_Detail Images URL | AT4: t_2_Detail Images URL | AU4: t_2_Detail Images URL | AV4: t_2_Detail Images URL | AW4: t_2_Detail Images URL | AX4: t_2_Detail Images URL | AY4: t_2_Detail Images URL | AZ4: t_2_Detail Images URL | BA4: t_2_Detail Images URL | BB4: t_2_Detail Images URL | BC4: t_2_Detail Images URL | BD4: t_2_Detail Images URL | BE4: t_2_Detail Images URL | BF4: t_2_Detail Images URL | BG4: t_2_Detail Images URL | BH4: t_2_Detail Images URL | BI4: t_2_Detail Images URL | BJ4: t_2_Detail Images URL | BK4: t_2_Detail Images URL | BL4: t_2_Detail Images URL | BM4: t_2_Detail Images URL | BN4: t_2_Detail Images URL | BO4: t_2_Detail Images URL | BP4: t_2_Detail Images URL | BQ4: t_2_Detail Images URL | BR4: t_2_Detail Images URL | BS4: t_2_Detail Images URL | BT4: t_2_Detail Images URL | BU4: t_2_Detail Images URL | BV4: t_2_Detail Images URL | BW4: t_2_Detail Images URL | BX4: t_2_Detail Images URL | BY4: t_2_Detail Images URL | BZ4: t_2_Detail Images URL | CA4: t_2_Detail Images URL | CB4: t_2_Detail Images URL | CC4: t_2_Detail Images URL | CD4: t_2_Detail Images URL | CE4: t_2_Detail Images URL | CF4: t_2_Detail Images URL | CG4: t_2_Detail Images URL | CH4: t_2_Detail Images URL | CI4: t_2_Detail Images URL | CJ4: t_2_Detail Images URL | CK4: t_2_Detail Images URL | CL4: t_2_Detail Images URL | CM4: t_2_Detail Images URL | CN4: t_2_Detail Images URL | CO4: t_2_Detail Images URL | CP4: t_2_Detail Images URL | CQ4: t_2_Detail Images URL | CR4: t_2_Detail Images URL | CS4: t_2_Detail Images URL | CT4: t_2_Detail Images URL | CU4: t_2_Detail Images URL | CV4: t_2_Detail Images URL | CW4: t_2_Detail Images URL | CX4: t_2_Detail Images URL | CY4: t_2_Detail Images URL | CZ4: t_2_Detail Images URL | DA4: t_2_Detail Images URL | DB4: t_2_Detail Images URL | DC4: t_2_Detail Images URL | DD4: t_2_Detail Images URL | DE4: t_2_Detail Images URL | DF4: t_2_Detail Images URL | DG4: t_2_Detail Images URL | DH4: t_2_Detail Images URL | DI4: t_2_Detail Images URL | DJ4: t_2_Detail Images URL | DK4: t_2_Detail Images URL | DL4: t_2_Detail Images URL | DM4: t_2_Detail Images URL | DN4: t_2_Detail Images URL | DO4: t_2_Detail Images URL | DP4: t_2_Detail Images URL | DQ4: t_2_Detail Images URL | DR4: t_2_Detail Video URL | DS4: t_3_Property:19 | DT4: t_3_Property:423 | DU4: t_3_Property:423 | DV4: t_3_Property:423 | DW4: t_3_Property:423 | DX4: t_3_Property:423 | DY4: t_3_Property:127 | DZ4: t_3_Property:121 | EA4: t_3_Property:130 | EB4: t_3_Property:2232 | EC4: t_3_Property:2233|2232 | ED4: t_3_Property:1561 | EE4: t_3_Property:1132|1561 | EF4: t_3_Property:1562|1561 | EG4: t_3_Property:137|1561 | EH4: t_3_Property:1563|1561 | EI4: t_3_Property:1485|1561 | EJ4: t_3_Property:2147|1561 | EK4: t_3_Property:2154|1561 | EL4: t_3_Property:111|1561 | EM4: t_3_Property:2028 - value|1561 | EN4: t_3_Property:2028 - unit|1561 | EO4: t_3_Property:3673 | EP4: t_3_Property:7644 | EQ4: t_4_Variation Theme | ER4: t_4_Custom Spec:1001 | ES4: t_4_Custom Spec:3001 | ET4: t_4_Custom Spec:18012 | EU4: t_4_Custom Spec:17017 | EV4: t_4_Custom Spec:18013 | EW4: t_4_Custom Spec:17018 | EX4: t_4_Custom Spec:18014 | EY4: t_4_Custom Spec:17019 | EZ4: t_4_Custom Spec:18016 | FA4: t_4_Custom Spec:17020 | FB4: t_4_Custom Spec:15998553 | FC4: t_4_Custom Spec:45114199 | FD4: t_4_Custom Spec:44214483 | FE4: t_6_SKU Images URL | FF4: t_6_SKU Images URL | FG4: t_6_SKU Images URL | FH4: t_6_SKU Images URL | FI4: t_6_SKU Images URL | FJ4: t_6_SKU Images URL | FK4: t_6_SKU Images URL | FL4: t_6_SKU Images URL | FM4: t_6_SKU Images URL | FN4: t_6_SKU Images URL | FO4: t_6_Dimensions | FP4: t_6_Quantity | FQ4: t_6_Base Price - USD | FR4: t_6_Reference Link | FS4: t_6_List Price - USD | FT4: t_6_Weight - lb | FU4: t_6_Length - in | FV4: t_6_Width - in | FW4: t_6_Height - in | FX4: t_6_SKU type | FY4: t_6_Individually packed | FZ4: t_6_Total packaging quantity | GA4: t_6_Packaging unit | GB4: t_6_Total item quantity | GC4: t_6_Item unit | GD4: t_6_Net content | GE4: t_6_Total net content | GF4: t_6_Net content unit | GG4: t_6_External Product ID Type | GH4: t_6_External Product ID | GI4: t_7_Shipping Template | GJ4: t_7_Handling Time | GK4: t_7_Import Designation | GL4: t_7_Fulfillment Channel | GM4: t_8_Country/Region of Origin | GN4: t_8_Province of Origin | GO4: t_8_SKU Packaging Information (with visible label) | GP4: t_8_SKU Packaging Information (with visible label) | GQ4: t_8_SKU Packaging Information (with visible label) | GR4: t_8_SKU Packaging Information (with visible label) | GS4: t_8_SKU Packaging Information (with visible label) | GT4: t_8_SKU Packaging Information (with visible label) | GU4: t_8_SKU Packaging Information (with visible label) | GV4: t_8_SKU Packaging Information (with visible label) | GW4: t_8_SKU Packaging Information (with visible label) | GX4: t_8_SKU Packaging Information (with visible label) | GY4: t_8_SKU Packaging Information (with visible label) | GZ4: t_8_SKU Packaging Information (with visible label) | HA4: t_8_SKU Packaging Information (with visible label) | HB4: t_8_SKU Packaging Information (with visible label) | HC4: t_8_SKU Packaging Information (with visible label) | HD4: t_8_SKU Packaging Information (with visible label) | HE4: t_8_SKU Packaging Information (with visible label) | HF4: t_8_SKU Packaging Information (with visible label) | HG4: t_8_SKU Packaging Information (with visible label) | HH4: t_8_SKU Packaging Information (with visible label) | HI4: t_8_SKU Packaging Information (with visible label) | HJ4: t_8_SKU Packaging Information (with visible label) | HK4: t_8_SKU Packaging Information (with visible label) | HL4: t_8_SKU Packaging Information (with visible label) | HM4: t_8_SKU Packaging Information (with visible label) | HN4: t_8_SKU Packaging Information (with visible label) | HO4: t_8_SKU Packaging Information (with visible label) | HP4: t_8_SKU Packaging Information (with visible label) | HQ4: t_8_SKU Packaging Information (with visible label) | HR4: t_8_SKU Packaging Information (with visible label) | HS4: t_8_SKU Packaging Information (with visible label) | HT4: t_8_SKU Packaging Information (with visible label) | HU4: t_8_SKU Packaging Information (with visible label) | HV4: t_8_SKU Packaging Information (with visible label) | HW4: t_8_SKU Packaging Information (with visible label) | HX4: t_8_SKU Packaging Information (with visible label) | HY4: t_8_SKU Packaging Information (with visible label) | HZ4: t_8_SKU Packaging Information (with visible label) | IA4: t_8_SKU Packaging Information (with visible label) | IB4: t_8_SKU Packaging Information (with visible label) | IC4: t_8_SKU Packaging Information (with visible label) | ID4: t_8_SKU Packaging Information (with visible label) | IE4: t_8_SKU Packaging Information (with visible label) | IF4: t_8_SKU Packaging Information (with visible label) | IG4: t_8_SKU Packaging Information (with visible label) | IH4: t_8_Origin Label & Manufacturer Information | II4: t_8_Origin Label & Manufacturer Information | IJ4: t_8_Origin Label & Manufacturer Information | IK4: t_8_Origin Label & Manufacturer Information | IL4: t_8_Origin Label & Manufacturer Information | IM4: t_8_Product Guide | IN4: t_8_Governance Property:1000000001 | IO4: t_8_Governance Property:1000000002
F5: =IFERROR(VLOOKUP(INDIRECT(ADDRESS(ROW(), COLUMN()-1)), 'Category Name'!$A:$B, 2, FALSE), "Please select the [category] first. After selecting, the full category path will be displayed here. Please do not modify the functions in the cells") -> 0
F6: =IFERROR(VLOOKUP(INDIRECT(ADDRESS(ROW(), COLUMN()-1)), 'Category Name'!$A:$B, 2, FALSE), "Please select the [category] first. After selecting, the full category path will be displayed here. Please do not modify the functions in the cells") -> 0
F7: =IFERROR(VLOOKUP(INDIRECT(ADDRESS(ROW(), COLUMN()-1)), 'Category Name'!$A:$B, 2, FALSE), "Please select the [category] first. After selecting, the full category path will be displayed here. Please do not modify the functions in the cells") -> 0
F8: =IFERROR(VLOOKUP(INDIRECT(ADDRESS(ROW(), COLUMN()-1)), 'Category Name'!$A:$B, 2, FALSE), "Please select the [category] first. After selecting, the full category path will be displayed here. Please do not modify the functions in the cells") -> 0
F9: =IFERROR(VLOOKUP(INDIRECT(ADDRESS(ROW(), COLUMN()-1)), 'Category Name'!$A:$B, 2, FALSE), "Please select the [category] first. After selecting, the full category path will be displayed here. Please do not modify the functions in the cells") -> 0
F10: =IFERROR(VLOOKUP(INDIRECT(ADDRESS(ROW(), COLUMN()-1)), 'Category Name'!$A:$B, 2, FALSE), "Please select the [category] first. After selecting, the full category path will be displayed here. Please do not modify the functions in the cells") -> 0
F11: =IFERROR(VLOOKUP(INDIRECT(ADDRESS(ROW(), COLUMN()-1)), 'Category Name'!$A:$B, 2, FALSE), "Please select the [category] first. After selecting, the full category path will be displayed here. Please do not modify the functions in the cells") -> 0
F12: =IFERROR(VLOOKUP(INDIRECT(ADDRESS(ROW(), COLUMN()-1)), 'Category Name'!$A:$B, 2, FALSE), "Please select the [category] first. After selecting, the full category path will be displayed here. Please do not modify the functions in the cells") -> 0
F13: =IFERROR(VLOOKUP(INDIRECT(ADDRESS(ROW(), COLUMN()-1)), 'Category Name'!$A:$B, 2, FALSE), "Please select the [category] first. After selecting, the full category path will be displayed here. Please do not modify the functions in the cells") -> 0
F14: =IFERROR(VLOOKUP(INDIRECT(ADDRESS(ROW(), COLUMN()-1)), 'Category Name'!$A:$B, 2, FALSE), "Please select the [category] first. After selecting, the full category path will be displayed here. Please do not modify the functions in the cells") -> 0
F15: =IFERROR(VLOOKUP(INDIRECT(ADDRESS(ROW(), COLUMN()-1)), 'Category Name'!$A:$B, 2, FALSE), "Please select the [category] first. After selecting, the full category path will be displayed here. Please do not modify the functions in the cells") -> 0
F16: =IFERROR(VLOOKUP(INDIRECT(ADDRESS(ROW(), COLUMN()-1)), 'Category Name'!$A:$B, 2, FALSE), "Please select the [category] first. After selecting, the full category path will be displayed here. Please do not modify the functions in the cells") -> 0
... F3000: =IFERROR(VLOOKUP(INDIRECT(ADDRESS(ROW(), COLUMN()-1)), 'Category Name'!$A:$B, 2, FALSE), "Please select the [category] first. After selecting, the full category path will be displayed here. Please do not modify the functions in the cells") -> 0

Sheet Instructions
A1: Using your Template
A2: Print this page
A3: On this page, you'll find the necessary details to generate, verify, and submit your template spreadsheet to Temu. For ease of reference throughout the process, we suggest printing out this page.
A4: Save a version of this file on your hard drive in Excel format. Next, input your product information into the Template tab, adhering to the following instructions.
A6: Image Tab
A7: Refer to the Images tab to familiarize yourself with Temu's guidelines for visual content. Ensure that the images you contribute to Temu align with these specified standards to maintain uniformity and excellence.
A8: It's important that an image is supplied for all products. Upload images by providing the image URL.
A10: Example Tab
A11: Check out the Example tab to view a sample of how to input product details. This is provided just for your guidance. Remember, to prevent the incorporation of incorrect product information into your inventory file, you should not edit your own products directly within the Example sheet.
A13: Template Tab
A14: Navigate to the Template tab to populate it with your listing specifics. When you select a Product Type 1. Recommended software: Due to file compatibility considerations, it is recommended to use Office - Excel to use and edit the template file; 2. Template integrity: Do not modify or delete the sheet names, column headers, or their order in the template file. For cells with dropdown enumerations, select and fill in values from the dropdown list. 3. After selecting the category you wish to publish in one row of the template; the file will then automatically display the required fields and valid values for each cell based on the selected category. a. Red borders indicate required fields. b. Gray shading indicates fields that should be left blank. c. White shading indicates optional fields. d. Please ensure that all required information in each row is filled in accurately and completely. Please enter the same product dimension information in all SKU rows. e. Although you don't have to fill in the optional fields, providing as much information as possible will help with product sales. 4. Units of measurement: the units in the template file are related to the publishing site a. The US marketplace uses the imperial system: the length unit is inches, the weight unit is pounds, and the currency unit is USD i. The length range is 0.1 in-999.9 in, with a maximum of 1 decimal point, and will be rounded up; ii. The weight range is 0.1 lb-9999.9 lb, with a maximum of 1 decimal point, and will be rounded up; iii. The price range is $0.01-$99999999.99, with a maximum of 2 decimal points, and will be rounded up. b. The Mexican marketplace uses the metric system: the length unit is centimeters, the weight unit is grams, and the currency unit is MXN i. The length range is 0.1 cm-9,999.9 cm, with a maximum of 1 decimal point, and will be rounded up; ii. The weight range is 0.1 g-9,999,999.9 g, with a maximum of 1 decimal place, and will be rounded up; iii. The price range is MX$0.01-MX$99999999.99, with a maximum of 2 decimal points, and will be rounded up. c. The Japan marketplace uses the metric system: the length unit is centimeters, the weight unit is grams, and the currency unit is JPY i. The length range is 0.1 cm-9,999.9 cm, with a maximum of 1 decimal point, and will be rounded up; ii. The weight range is 0.1 g-9,999,999.9 g, with a maximum of 1 decimal place, and will be rounded up; iii. The price range is 円1-円9,999,999,999, with a maximum of 0 decimal points, and will be rounded up. d. The German, Italian, French and Spanish marketplaces all use the metric system: the length unit is centimeters, the weight unit is grams, and the currency unit is EUR i. The length range is 0.1 cm-9,999.9 cm, with a maximum of 1 decimal point, and will be rounded up; ii. The weight range is 0.1 g-9,999,999.9 g, with a maximum of 1 decimal place, and will be rounded up; iii. The price range is €0.01-€99999999.99, with a maximum of 2 decimal places, and will be rounded up. e. Marketplace in UK is metric: the length unit is centimeters, the weight unit is grams, and the currency unit is GBP i. The length range is 0.1 cm-9,999.9 cm, with a maximum of 1 decimal point, and will be rounded up; ii. The weight range is 0.1 g-9,999,999.9 g, with a maximum of 1 decimal place, and will be rounded up; iii. The price range is £0.01-£99999999.99, with a maximum of 2 decimal places, and will be rounded up. 5. Qualifications and photos: Different compliance requirements may be imposed under varying conditions during the product's ongoing operation. For products that require these materials, you can submit the documents and then access the product compliance center to confirm and provide them. 6. Quantity limit: In each file, up to 2000 lines of content are allowed, otherwise products will not be able to be added to the file. Alternatively, you can save the "Template" tab (only) as Unicode Text (*.txt)): right-click the "Template" tab, move or copy, select "New book" and "Create a Copy," then choose "File" and save in the correct file format. Files uploaded this way can contain up to 50,000 lines. 7. Duplicate columns: The Excel file is collapsed by default. You can click on 1 and 2 at the top of the Excel file.
A17: Submit the spreadsheet
... A23: From time to time, Temu will update valid values, data validation rules, explanatory text, and requirements. Please use the latest generated template files.

Sheet Images
A1: Image Standards
A3: Every product on Temu needs one or more product images. Choose images that are clear, straightforward, and easy to understand. They must accurately represent the product and be information-rich and attractively presented. Show only the product that is being offered for sale. Whenever possible, provide several images, with each one showing different angles and details of the product. This is your opportunity to show your product to your customer, so quality matters.
A4: We reserve the right to reject images that do not meet our image standards.
A5: It is your responsibility to ensure that you have all necessary rights to the images you submit.
A7: SKU images
A9: The SKU images will be displayed at the top of the product page. Different SKU images will form a carousel of the product.
A10: For apparel products, the images you upload should be with a maximum size of 3MB, an aspect ratio of 3:4, width ≥ 1340px, height ≥ 1785px. The SKUs with the same color will share a set of carousel images.
A11: For non-apparel products, the images you upload should be with a maximum size of 3MB, an aspect ratio of 1:1, and width and height ≥ 800px.
A12: You can upload up to ten images, with each cell containing one image URL.
A14: Product video
A16: The product video will be displayed at the top of the product page.
A17: The video you upload should be with a maximum size of 100MB, a length not exceeding 180 seconds, and a minimum resolution of 720P.
... A32: Upload the video with a maximum size of 300MB, a length not exceeding 180 seconds, an aspect ratio of either 1:1, 4:3, or 16:9, and a minimum resolution of 720P.

Sheet Example
A1: 1. Besides reviewing the contents of the Example tab, kindly peruse the Instructions tab provided in this document.
A2: 2. Be aware that the examples provided serve merely as illustrations. The columns appearing in your tailored template will vary according to the selected Category. Utilize the Template tab to generate the template spreadsheet.
A3: 3. Some of the optional columns are collapsed for the purpose of better representation. Please show those collapsed areas by clicking '+' button on the corresponding column or section
A4: 4. Errors when you submit a product entry can be resolved by viewing the Processing results, or by contacting Seller Support.
A5: Some fields are Required. Other are Optional. | B5: Product Identity | H5: Product Description | BN5: Product Detail | GT5: Sale Property (At Least One, At Most Two) | HL5: Size Chart | IE5: Variations | IZ5: Offer | JD5: Qualifications
B6: Category | C6: Product Name | D6: Contribution Goods | E6: Contribution SKU | F6: Brand | G6: Trademark | H6: Product Description | I6: Bullet Point | J6: Bullet Point | K6: Bullet Point | L6: Bullet Point | M6: Bullet Point | N6: Bullet Point | O6: Detail Images URL | P6: Detail Images URL | Q6: Detail Images URL | R6: Detail Images URL | S6: Detail Images URL | T6: Detail Images URL | U6: Detail Images URL | V6: Detail Images URL | W6: Detail Images URL | X6: Detail Images URL | Y6: Detail Images URL | Z6: Detail Images URL | AA6: Detail Images URL | AB6: Detail Images URL | AC6: Detail Images URL | AD6: Detail Images URL | AE6: Detail Images URL | AF6: Detail Images URL | AG6: Detail Images URL | AH6: Detail Images URL | AI6: Detail Images URL | AJ6: Detail Images URL | AK6: Detail Images URL | AL6: Detail Images URL | AM6: Detail Images URL | AN6: Detail Images URL | AO6: Detail Images URL | AP6: Detail Images URL | AQ6: Detail Images URL | AR6: Detail Images URL | AS6: Detail Images URL | AT6: Detail Images URL | AU6: Detail Images URL | AV6: Detail Images URL | AW6: Detail Images URL | AX6: Detail Images URL | AY6: Detail Images URL | AZ6: Detail Images URL | BA6: Detail Images URL | BB6: Detail Images URL | BC6: Detail Images URL | BD6: Detail Images URL | BE6: Detail Images URL | BF6: Detail Images URL | BG6: Detail Images URL | BH6: Detail Images URL | BI6: Detail Images URL | BJ6: Detail Images URL | BK6: Detail Images URL | BL6: Detail Images URL | BM6: Detail Video URL | BN6: 4115 - Shelf Life - value | BO6: 4115 - Shelf Life - unit | BP6: 4118 - Speciality | BQ6: 4118 - Speciality | BR6: 4118 - Speciality | BS6: 4119 - Item Weight - value | BT6: 4119 - Item Weight - unit | BU6: 4120 - Package Weight - value | BV6: 4120 - Package Weight - unit | BW6: 4121 - Allergen Information | BX6: 4121 - Allergen Information | BY6: 4121 - Allergen Information | BZ6: 4121 - Allergen Information | CA6: 4121 - Allergen Information | CB6: 4121 - Allergen Information | CC6: 4121 - Allergen Information | CD6: 4121 - Allergen Information | CE6: 4121 - Allergen Information | CF6: 4121 - Allergen Information | CG6: 195 - Diet Type | CH6: 195 - Diet Type | CI6: 195 - Diet Type | CJ6: 6160 - Brand Name | CK6: 6210 - USDA certified | CL6: 4110 - Production Date | CM6: 6440 - best before | CN6: 361 - Package Quantity | CO6: 12 - Material | CP6: 12 - Material | CQ6: 12 - Material | CR6: 12 - Material | CS6: 12 - Material | CT6: 4134 - Publisher | CU6: 4130 - Country/Region Of Origin | CV6: 4137 - Author | CW6: 1120 - Set or not | CX6: 4133 - Binding Type | CY6: 4123 - Languages | CZ6: 4123 - Languages | DA6: 4123 - Languages | DB6: 4142 - Year Of Publication | DC6: 4124 - Number Of Pages (pages) - value | DD6: 4124 - Number Of Pages (pages) - unit | DE6: 4131 - Number Of Words (10,000 Words) | DF6: 4127 - Product Weight (g) - value | DG6: 4127 - Product Weight (g) - unit | DH6: 4128 - Maximum Reading Age (years) - value | DI6: 4128 - Maximum Reading Age (years) - unit | DJ6: 4129 - Minimum Reading Age (years) - value | DK6: 4129 - Minimum Reading Age (years) - unit | DL6: 121 - Material | DM6: 121 - Material | DN6: 121 - Material | DO6: 121 - Material | DP6: 121 - Material | DQ6: 132 - Finish Type | DR6: 210 - Furniture Finish | DS6: 19 - Style | DT6: 1561 - Power Supply | DU6: 1132 - Operating Voltage | DV6: 1485 - Plug Type | DW6: 1485 - Plug Type | DX6: 1485 - Plug Type | DY6: 1571 - Acceptable Voltage Range | DZ6: 4102 - Contain Wooden Materials | EA6: 4097 - Tree Species | EB6: 4097 - Tree Species | EC6: 4098 - Wood Formation Type | ED6: 4098 - Wood Formation Type | EE6: 4098 - Wood Formation Type | EF6: 4099 - Fiberboard Density | EG6: 6171 - Wether Independent | EH6: 6172 - Closed Storage Capacity | EI6: 6173 - Height After Assembly | EJ6: 6174 - Physical Weight | EK6: 2153 - Battery Properties | EL6: 2147 - Rechargeable Battery | EM6: 2154 - Solar Battery Type | EN6: 3740 - Non-rechargeable Battery | EO6: 2028 - Battery Capacity (mAh) - value | EP6: 2028 - Battery Capacity (mAh) - unit | EQ6: 63 - Color | ER6: 15 - Composition:Nylon | ES6: 15 - Composition:Polyester | ET6: 15 - Composition:Polyamide | EU6: 15 - Composition:Elastane | EV6: 15 - Composition:Spandex | EW6: 15 - Composition:Acrylic | EX6: 15 - Composition:Cotton | EY6: 15 - Composition:Silk | EZ6: 15 - Composition:Linen | FA6: 15 - Composition:Modal | FB6: 15 - Composition:Viscose | FC6: 15 - Composition:Rayon | FD6: 15 - Composition:Carbon | FE6: 15 - Composition:Metal | FF6: 15 - Composition:Wool | FG6: 15 - Composition:Cashmere | FH6: 15 - Composition:Mohair | FI6: 15 - Composition:Rabbit Hair | FJ6: 15 - Composition:Bovine Leather | FK6: 15 - Composition:Sheep Leather | FL6: 15 - Composition:Pig Leather | FM6: 15 - Composition:Polyurethane | FN6: 15 - Composition:Polyvinyl Chloride | FO6: 15 - Composition:Cupro | FP6: 15 - Composition:Lyocell | FQ6: 15 - Composition:Acetate | FR6: 15 - Composition:Down | FS6: 15 - Composition:Feather | FT6: 15 - Composition:Duck Down | FU6: 15 - Composition:Alpaca | FV6: 15 - Composition:Metallized Fibres | FW6: 15 - Composition:Polypropylene fibers | FX6: 15 - Composition:Other Fibers | FY6: 28 - Length | FZ6: 74 - Belt | GA6: 29 - Sleeve Length | GB6: 27 - Sleeve Type | GC6: 94 - Chest Pad | GD6: 83 - Details | GE6: 26 - Pattern | GF6: 24 - Sheer | GG6: 22 - Fabric | GH6: 86 - Placket Type | GI6: 78 - Lining | GJ6: 113 - Contour | GK6: 76 - Season | GL6: 20 - Operation Instruction | GM6: 114 - Fit Type | GN6: 1352 - Fabric Elasticity | GO6: 1919 - Printing Type | GP6: 2103 - Style source | GQ6: 1192 - Weaving Method | GR6: 21 - Collar Style | GS6: 6227 - Collection | GT6: Variation Theme | GU6: Size Family | GV6: Sub-Size Family | GW6: Size | GX6: Color | GY6: Color | GZ6: Size | HA6: Style | HB6: Material | HC6: Flavors | HD6: Applicable People | HE6: Capacity | HF6: Composition | HG6: Weight | HH6: Items | HI6: Quantity | HJ6: Model | HK6: Hair Length | HL6: Unit | HM6: US Size | HN6: Tops - Product - Shoulder width | HO6: Tops - Product - Bust size | HP6: Tops - Product - Clothes length | HQ6: Tops - Product - Sleeve length | HR6: Tops - Product - Waist size | HS6: Tops - Product - Underbust | HT6: Tops - Product - Neck | HU6: Tops - Product - Hem | HV6: Tops - Product - Cuffs | HW6: Tops - Body - Bust - min | HX6: Tops - Body - Bust - max | HY6: Tops - Body - Waist - min | HZ6: Tops - Body - Waist - max | IA6: Tops - Body - Hips - min | IB6: Tops - Body - Hips - max | IC6: Tops - Body - Height - min | ID6: Tops - Body - Height - max | IE6: SKU Images URL | IF6: SKU Images URL | IG6: SKU Images URL | IH6: SKU Images URL | II6: SKU Images URL | IJ6: SKU Images URL | IK6: SKU Images URL | IL6: SKU Images URL | IM6: SKU Images URL | IN6: SKU Images URL | IO6: Dimensions | IP6: Condition | IQ6: Quantity | IR6: Base Price - USD | IS6: List Price - USD | IT6: Weight - lb | IU6: Length - in | IV6: Width - in | IW6: Height - in | IX6: External Product ID Type | IY6: External Product ID | IZ6: Handling Time | JA6: Shipping Template | JB6: Import Designation | JC6: Fulfillment Channel | JD6: Product Guide | JE6: California Proposition 65 Warning Type | JF6: California Proposition 65 Warning Type | JG6: California Proposition 65 Warning Type | JH6: California Proposition 65 Chemical Names | JI6: California Proposition 65 Chemical Names | JJ6: California Proposition 65 Chemical Names | JK6: California Proposition 65 Chemical Names | JL6: California Proposition 65 Chemical Names | JM6: California Proposition 65 Chemical Names | JN6: California Proposition 65 Chemical Names | JO6: California Proposition 65 Chemical Names | JP6: California Proposition 65 Chemical Names | JQ6: California Proposition 65 Chemical Names | JR6: California Proposition 65 Chemical Names | JS6: California Proposition 65 Chemical Names | JT6: California Proposition 65 Chemical Names | JU6: California Proposition 65 Chemical Names | JV6: California Proposition 65 Chemical Names | JW6: California Proposition 65 Chemical Names | JX6: California Proposition 65 Chemical Names | JY6: California Proposition 65 Chemical Names | JZ6: California Proposition 65 Chemical Names | KA6: California Proposition 65 Chemical Names
A7: Example 1: This is an example of providing a new listing. This example has no variation and is listed as a single detail page. | B7: 29069 | C7: Example Women T-shirt, 156 Black T-shirt | D7: EXAMPLE-156-US-Black-one-size | E7: EXAMPLE-156-US-Black-one-size | H7: Unleash your personal style with our classic fit tee. Crafted from 100% cotton, it offers unmatched comfort and durability. The tee features a unique, eye-catching graphic that embodies modern chic. Perfect for casual outings or layering under a jacket, this T-shirt is versatile for any occasion. With a breathable fabric that holds its shape, it's a wardrobe staple you'll reach for time and again. Make a statement and stay cozy in a shirt designed to express who you are. (Character count: 493) | I7: 100% premium cotton for ultimate comfort. | J7: Timeless design meets modern style. | K7: Durable fabric, perfect for daily wear | L7: Machine washable and easy to care for. | M7: Versatile fit for every body type. | O7: http://www.companyname.com/images/1250.main.jpg | P7: http://www.companyname.com/images/1250.main.jpg | Q7: http://www.companyname.com/images/1250.main.jpg | R7: http://www.companyname.com/images/1250.main.jpg | CO7: Recycle Polyester | DS7: Y2K | ER7: 32 | ES7: 28 | ET7: 40 | FY7: Short Length | FZ7: Yes | GA7: Long Sleeve | GB7: Raglan sleeve | GC7: No Padding | GD7: Fake Pockets | GE7: Mushroom | GF7: No | GG7: Non-Stretch | GH7: Half Placket | GI7: Cashmere | GJ7: H | GK7: Fall | GL7: Do not wash | GM7: Regular | GN7: No Elasticity | GO7: Positioning Printing | GP7: Buyer provides | GQ7: Woven | GR7: Off the Shoulder | GS7: Middle East | GT7: Size × Color | GU7: US/EU size | GV7: One Size | GW7: one-size | GX7: Black | HL7: Inch | HM7: one-size | HO7: 36 | HP7: 28 | HW7: 33.9 | HX7: 35.5 | HY7: 26 | HZ7: 27.6 | IA7: 35.9 | IB7: 37.4 | IE7: http://www.companyname.com/images/1250.main.jpg | IF7: http://www.companyname.com/images/1250.main.jpg | IG7: http://www.companyname.com/images/1250.main.jpg | IO7: http://www.companyname.com/images/1250.main.jpg | IP7: Used - Like new | IQ7: 5 | IR7: 2.99 | IS7: 5.99 | IT7: 9.2 | IU7: 2 | IV7: 3 | IW7: 4 | IZ7: 1 Day | JA7: test1 | JB7: Imported | JC7: I will ship this item myself | JE7: No Warning Applicable
B8: 12408 | C8: Example reclaimed Cabinet Solid Wood with 4 Drawers | D8: EXAMPLE-576-Brown | E8: EXAMPLE-576-Brown | DL8: Wood | DQ8: Painted | DR8: Cedar | DS8: Vintage | DT8: Plug Powered | DU8: 110V (included)-240V (included) | DV8: US Plug | DZ8: Yes | EA8: Hardwood | EC8: Block Board (large Core Board) | EG8: Yes | EH8: <3.2 Cubic Feet | EI8: <27 Inches | EJ8: <30 Lbs | EK8: Without Battery | EQ8: Red | GT8: Color × Style | GY8: Red | HA8: Vintage | IE8: http://www.companyname.com/images/1250.main.jpg | IF8: http://www.companyname.com/images/1250.main.jpg | IG8: http://www.companyname.com/images/1250.main.jpg | IO8: http://www.companyname.com/images/1250.main.jpg | IP8: Used - Very good | IQ8: 0 | IR8: 2.99 | IS8: 5.99 | IT8: 9.2 | IU8: 2 | IV8: 3 | IW8: 4 | IZ8: 1 Day | JA8: test1 | JB8: Imported | JC8: I will ship this item myself | JD8: http://www.companyname.com/images/productguide.pdf | JE8: Chemical | JF8: On Product Cancer | JH8: A-alpha-C (2-Amino-9H-pyrido[2,3-b]indole) | JI8: Acetaldehyde
B9: 44936 | C9: Example book for US with isbn | D9: EXAMPLEISBN9787040205190 | E9: EXAMPLEISBN9787040205190 | CT9: Example publisher | CU9: USA | CV9: Example author | CW9: No | CX9: Paperback | CY9: English | DB9: 44604 | DC9: 300 | DD9: Page | DE9: 1000 | DF9: 200 | DG9: g | DH9: 99 | DI9: years old | DJ9: 1 | DK9: years old | GT9: Items | HH9: Example book for US with isbn | IE9: http://www.companyname.com/images/1250.main.jpg | IF9: http://www.companyname.com/images/1250.main.jpg | IG9: http://www.companyname.com/images/1250.main.jpg | IO9: http://www.companyname.com/images/1250.main.jpg | IP9: Used - Good | IQ9: 20 | IR9: 7.82 | IS9: 10.23 | IT9: 9.2 | IU9: 2 | IV9: 3 | IW9: 4 | IX9: ISBN | IY9: 920000021 | IZ9: 1 Day | JA9: test1 | JB9: Imported | JC9: I will ship this item myself | JE9: No Warning Applicable
B10: 42550 | C10: Example food Potato Chips Pack of 6 - 80g per bag | D10: EXAMPLE-Pack6 - 80g | E10: EXAMPLE-Pack6 - 80g | BN10: 30 | BO10: Day | BP10: Wild-Caught | BQ10: Certified-Humane-Raised-And-Handled | BS10: 90 | BT10: g | BU10: 106 | BV10: g | BW10: Contains cow's milk | BX10: Contains Peanuts | CG10: Plant Based | CJ10: Example brand name | CK10: less than 70% organic ingredients | CL10: 45550 | CM10: 45641 | GT10: Weight | HG10: 90g | IE10: http://www.companyname.com/images/1250.main.jpg | IF10: http://www.companyname.com/images/1250.main.jpg | IG10: http://www.companyname.com/images/1250.main.jpg | IO10: http://www.companyname.com/images/1250.main.jpg | IP10: Used - Acceptable | IQ10: 20 | IR10: 5.39 | IS10: 7.39 | IT10: 9.2 | IU10: 2 | IV10: 3 | IW10: 4 | IZ10: 1 Day | JA10: test1 | JB10: Imported | JC10: I will ship this item myself | JE10: Food
A12: Example 2: This is an example of a product with 1 variation theme (i.e., size) with 3 variations. These are 3 "Child" SKUs in a "Parent" Goods. Note: For product-level information such as Product Name, Product Description, Product Detail, Offer, Qualifications, please ensure that each line is filled out correctly and the information is consistently entered. | B12: 29069 | C12: Example Women T-shirt, 156 Black T-shirt | D12: EXAMPLE-156-US-Black | E12: EXAMPLE-156-US-Black-S | H12: Unleash your personal style with our classic fit tee. Crafted from 100% cotton, it offers unmatched comfort and durability. The tee features a unique, eye-catching graphic that embodies modern chic. Perfect for casual outings or layering under a jacket, this T-shirt is versatile for any occasion. With a breathable fabric that holds its shape, it's a wardrobe staple you'll reach for time and again. Make a statement and stay cozy in a shirt designed to express who you are. (Character count: 493) | I12: 100% premium cotton for ultimate comfort. | J12: Timeless design meets modern style. | K12: Durable fabric, perfect for daily wear | L12: Machine washable and easy to care for. | M12: Versatile fit for every body type. | O12: http://www.companyname.com/images/1250.main.jpg | P12: http://www.companyname.com/images/1250.main.jpg | Q12: http://www.companyname.com/images/1250.main.jpg | R12: http://www.companyname.com/images/1250.main.jpg | CO12: Recycle Polyester | DS12: Y2K | ER12: 32 | ES12: 28 | ET12: 40 | FY12: Short Length | FZ12: Yes | GA12: Long Sleeve | GB12: Raglan sleeve | GC12: No Padding | GD12: Fake Pockets | GE12: Mushroom | GF12: No | GG12: Non-Stretch | GH12: Half Placket | GI12: Cashmere | GJ12: H | GK12: Fall | GL12: Do not wash | GM12: Regular | GN12: No Elasticity | GO12: Positioning Printing | GP12: Buyer provides | GQ12: Woven | GR12: Off the Shoulder | GS12: Middle East | GT12: Size × Color | GU12: US/EU size | GV12: Alpha | GW12: S | GX12: Black | HL12: Inch | HM12: 0 | HO12: 36 | HP12: 28 | HW12: 33.9 | HX12: 35.5 | HY12: 26 | HZ12: 27.6 | IA12: 35.9 | IB12: 37.4 | IE12: http://www.companyname.com/images/1250.main.jpg | IF12: http://www.companyname.com/images/1250.main.jpg | IG12: http://www.companyname.com/images/1250.main.jpg | IO12: http://www.companyname.com/images/1250.main.jpg | IP12: Used - Like new | IQ12: 5 | IR12: 2.99 | IS12: 5.99 | IT12: 9.2 | IU12: 2 | IV12: 3 | IW12: 4 | IZ12: 1 Day | JA12: test1 | JB12: Imported | JC12: I will ship this item myself | JE12: No Warning Applicable
B13: 29069 | C13: Example Women T-shirt, 156 Black T-shirt | D13: EXAMPLE-156-US-Black | E13: EXAMPLE-156-US-Black-M | H13: Unleash your personal style with our classic fit tee. Crafted from 100% cotton, it offers unmatched comfort and durability. The tee features a unique, eye-catching graphic that embodies modern chic. Perfect for casual outings or layering under a jacket, this T-shirt is versatile for any occasion. With a breathable fabric that holds its shape, it's a wardrobe staple you'll reach for time and again. Make a statement and stay cozy in a shirt designed to express who you are. (Character count: 493) | I13: 100% premium cotton for ultimate comfort. | J13: Timeless design meets modern style. | K13: Durable fabric, perfect for daily wear | L13: Machine washable and easy to care for. | M13: Versatile fit for every body type. | O13: http://www.companyname.com/images/1250.main.jpg | P13: http://www.companyname.com/images/1250.main.jpg | Q13: http://www.companyname.com/images/1250.main.jpg | R13: http://www.companyname.com/images/1250.main.jpg | CO13: Recycle Polyester | DS13: Y2K | ER13: 32 | ES13: 28 | ET13: 40 | FY13: Short Length | FZ13: Yes | GA13: Long Sleeve | GB13: Raglan sleeve | GC13: No Padding | GD13: Fake Pockets | GE13: Mushroom | GF13: No | GG13: Non-Stretch | GH13: Half Placket | GI13: Cashmere | GJ13: H | GK13: Fall | GL13: Do not wash | GM13: Regular | GN13: No Elasticity | GO13: Positioning Printing | GP13: Buyer provides | GQ13: Woven | GR13: Off the Shoulder | GS13: Middle East | GT13: Size × Color | GU13: US/EU size | GV13: Alpha | GW13: M | GX13: Black | HL13: Inch | HM13: 2 | HO13: 40 | HP13: 29 | HW13: 35.5 | HX13: 37 | HY13: 27.6 | HZ13: 29.2 | IA13: 27.4 | IB13: 39 | IE13: http://www.companyname.com/images/1250.main.jpg | IF13: http://www.companyname.com/images/1250.main.jpg | IG13: http://www.companyname.com/images/1250.main.jpg | IO13: http://www.companyname.com/images/1250.main.jpg | IP13: Used - Like new | IQ13: 5 | IR13: 2.99 | IS13: 5.99 | IT13: 9.2 | IU13: 2 | IV13: 3 | IW13: 4 | IZ13: 1 Day | JA13: test1 | JB13: Imported | JC13: I will ship this item myself | JE13: No Warning Applicable
B14: 29069 | C14: Example Women T-shirt, 156 Black T-shirt | D14: EXAMPLE-156-US-Black | E14: EXAMPLE-156-US-Black-L | H14: Unleash your personal style with our classic fit tee. Crafted from 100% cotton, it offers unmatched comfort and durability. The tee features a unique, eye-catching graphic that embodies modern chic. Perfect for casual outings or layering under a jacket, this T-shirt is versatile for any occasion. With a breathable fabric that holds its shape, it's a wardrobe staple you'll reach for time and again. Make a statement and stay cozy in a shirt designed to express who you are. (Character count: 493) | I14: 100% premium cotton for ultimate comfort. | J14: Timeless design meets modern style. | K14: Durable fabric, perfect for daily wear | L14: Machine washable and easy to care for. | M14: Versatile fit for every body type. | O14: http://www.companyname.com/images/1250.main.jpg | P14: http://www.companyname.com/images/1250.main.jpg | Q14: http://www.companyname.com/images/1250.main.jpg | R14: http://www.companyname.com/images/1250.main.jpg | CO14: Recycle Polyester | DS14: Y2K | ER14: 32 | ES14: 28 | ET14: 40 | FY14: Short Length | FZ14: Yes | GA14: Long Sleeve | GB14: Raglan sleeve | GC14: No Padding | GD14: Fake Pockets | GE14: Mushroom | GF14: No | GG14: Non-Stretch | GH14: Half Placket | GI14: Cashmere | GJ14: H | GK14: Fall | GL14: Do not wash | GM14: Regular | GN14: No Elasticity | GO14: Positioning Printing | GP14: Buyer provides | GQ14: Woven | GR14: Off the Shoulder | GS14: Middle East | GT14: Size × Color | GU14: US/EU size | GV14: Alpha | GW14: L | GX14: Black | HL14: Inch | HM14: 4 | HO14: 44 | HP14: 30 | HW14: 37.4 | HX14: 39.8 | HY14: 29.6 | HZ14: 31.9 | IA14: 39.4 | IB14: 41.8 | IE14: http://www.companyname.com/images/1250.main.jpg | IF14: http://www.companyname.com/images/1250.main.jpg | IG14: http://www.companyname.com/images/1250.main.jpg | IO14: http://www.companyname.com/images/1250.main.jpg | IP14: Used - Like new | IQ14: 5 | IR14: 2.99 | IS14: 5.99 | IT14: 9.2 | IU14: 2 | IV14: 3 | IW14: 4 | IZ14: 1 Day | JA14: test1 | JB14: Imported | JC14: I will ship this item myself | JE14: No Warning Applicable
B15: 12408 | C15: Example reclaimed Cabinet Solid Wood with 4 Drawers | D15: EXAMPLE-576 | E15: EXAMPLE-576-Brown | DL15: Wood | DQ15: Painted | DR15: Cedar | DS15: Vintage | DT15: Plug Powered | DU15: 110V (included)-240V (included) | DV15: US Plug | DZ15: Yes | EA15: Hardwood | EC15: Block Board (large Core Board) | EG15: Yes | EH15: <3.2 Cubic Feet | EI15: <27 Inches | EJ15: <30 Lbs | EK15: Without Battery | EQ15: Red | GT15: Color | GY15: Brown | IE15: http://www.companyname.com/images/1250.main.jpg | IF15: http://www.companyname.com/images/1250.main.jpg | IG15: http://www.companyname.com/images/1250.main.jpg | IO15: http://www.companyname.com/images/1250.main.jpg | IP15: Used - Very good | IQ15: 5 | IR15: 2.99 | IS15: 5.99 | IT15: 9.2 | IU15: 2 | IV15: 3 | IW15: 4 | IZ15: 1 Day | JA15: test1 | JB15: Imported | JC15: I will ship this item myself | JE15: No Warning Applicable
B16: 12408 | C16: Example reclaimed Cabinet Solid Wood with 4 Drawers | D16: EXAMPLE-576 | E16: EXAMPLE-576-white | DL16: Wood | DQ16: Painted | DR16: Cedar | DS16: Vintage | DT16: Plug Powered | DU16: 110V (included)-240V (included) | DV16: US Plug | DZ16: Yes | EA16: Hardwood | EC16: Block Board (large Core Board) | EG16: Yes | EH16: <3.2 Cubic Feet | EI16: <27 Inches | EJ16: <30 Lbs | EK16: Without Battery | EQ16: Red | GT16: Color | GY16: white | IE16: http://www.companyname.com/images/1250.main.jpg | IF16: http://www.companyname.com/images/1250.main.jpg | IG16: http://www.companyname.com/images/1250.main.jpg | IO16: http://www.companyname.com/images/1250.main.jpg | IP16: Used - Very good | IQ16: 5 | IR16: 2.99 | IS16: 5.99 | IT16: 9.2 | IU16: 2 | IV16: 3 | IW16: 4 | IZ16: 1 Day | JA16: test1 | JB16: Imported | JC16: I will ship this item myself | JE16: No Warning Applicable
B17: 12408 | C17: Example reclaimed Cabinet Solid Wood with 4 Drawers | D17: EXAMPLE-576 | E17: EXAMPLE-576-red | DL17: Wood | DQ17: Painted | DR17: Cedar | DS17: Vintage | DT17: Plug Powered | DU17: 110V (included)-240V (included) | DV17: US Plug | DZ17: Yes | EA17: Hardwood | EC17: Block Board (large Core Board) | EG17: Yes | EH17: <3.2 Cubic Feet | EI17: <27 Inches | EJ17: <30 Lbs | EK17: Without Battery | EQ17: Red | GT17: Color | GY17: red | IE17: http://www.companyname.com/images/1250.main.jpg | IF17: http://www.companyname.com/images/1250.main.jpg | IG17: http://www.companyname.com/images/1250.main.jpg | IO17: http://www.companyname.com/images/1250.main.jpg | IP17: Used - Very good | IQ17: 5 | IR17: 2.99 | IS17: 5.99 | IT17: 9.2 | IU17: 2 | IV17: 3 | IW17: 4 | IZ17: 1 Day | JA17: test1 | JB17: Imported | JC17: I will ship this item myself | JE17: No Warning Applicable
A19: Example 3: This is an example of a product with 2 variation themes (i.e., size and color) with 4 variations. These are 4 "Child" SKUs in a "Parent" Goods. Note: For product-level information such as Product Name, Product Description, Product Detail, Offer, Qualifications, please ensure that each line is filled out correctly and the information is consistently entered. | B19: 29069 | C19: Example Women T-shirt, 156 Black T-shirt | D19: EXAMPLE-156-US | E19: EXAMPLE-156-US-Black-S | H19: Unleash your personal style with our classic fit tee. Crafted from 100% cotton, it offers unmatched comfort and durability. The tee features a unique, eye-catching graphic that embodies modern chic. Perfect for casual outings or layering under a jacket, this T-shirt is versatile for any occasion. With a breathable fabric that holds its shape, it's a wardrobe staple you'll reach for time and again. Make a statement and stay cozy in a shirt designed to express who you are. (Character count: 493) | I19: 100% premium cotton for ultimate comfort. | J19: Timeless design meets modern style. | K19: Durable fabric, perfect for daily wear | L19: Machine washable and easy to care for. | M19: Versatile fit for every body type. | O19: http://www.companyname.com/images/1250.main.jpg | P19: http://www.companyname.com/images/1250.main.jpg | Q19: http://www.companyname.com/images/1250.main.jpg | R19: http://www.companyname.com/images/1250.main.jpg | CO19: Recycle Polyester | DS19: Y2K | ER19: 32 | ES19: 28 | ET19: 40 | FY19: Short Length | FZ19: Yes | GA19: Long Sleeve | GB19: Raglan sleeve | GC19: No Padding | GD19: Fake Pockets | GE19: Mushroom | GF19: No | GG19: Non-Stretch | GH19: Half Placket | GI19: Cashmere | GJ19: H | GK19: Fall | GL19: Do not wash | GM19: Regular | GN19: No Elasticity | GO19: Positioning Printing | GP19: Buyer provides | GQ19: Woven | GR19: Off the Shoulder | GS19: Middle East | GT19: Size × Color | GU19: US/EU size | GV19: Alpha | GW19: S | GX19: Black | HL19: Inch | HM19: 0 | HO19: 36 | HP19: 28 | HW19: 33.9 | HX19: 35.5 | HY19: 26 | HZ19: 27.6 | IA19: 35.9 | IB19: 37.4 | IE19: http://www.companyname.com/images/1250.main.jpg | IF19: http://www.companyname.com/images/1250.main.jpg | IG19: http://www.companyname.com/images/1250.main.jpg | IO19: http://www.companyname.com/images/1250.main.jpg | IP19: Used - Like new | IQ19: 5 | IR19: 2.99 | IS19: 5.99 | IT19: 9.2 | IU19: 2 | IV19: 3 | IW19: 4 | IZ19: 1 Day | JA19: test1 | JB19: Imported | JC19: I will ship this item myself | JE19: No Warning Applicable
B20: 29069 | C20: Example Women T-shirt, 156 Black T-shirt | D20: EXAMPLE-156-US | E20: EXAMPLE-156-US-Black-M | H20: Unleash your personal style with our classic fit tee. Crafted from 100% cotton, it offers unmatched comfort and durability. The tee features a unique, eye-catching graphic that embodies modern chic. Perfect for casual outings or layering under a jacket, this T-shirt is versatile for any occasion. With a breathable fabric that holds its shape, it's a wardrobe staple you'll reach for time and again. Make a statement and stay cozy in a shirt designed to express who you are. (Character count: 493) | I20: 100% premium cotton for ultimate comfort. | J20: Timeless design meets modern style. | K20: Durable fabric, perfect for daily wear | L20: Machine washable and easy to care for. | M20: Versatile fit for every body type. | O20: http://www.companyname.com/images/1250.main.jpg | P20: http://www.companyname.com/images/1250.main.jpg | Q20: http://www.companyname.com/images/1250.main.jpg | R20: http://www.companyname.com/images/1250.main.jpg | CO20: Recycle Polyester | DS20: Y2K | ER20: 32 | ES20: 28 | ET20: 40 | FY20: Short Length | FZ20: Yes | GA20: Long Sleeve | GB20: Raglan sleeve | GC20: No Padding | GD20: Fake Pockets | GE20: Mushroom | GF20: No | GG20: Non-Stretch | GH20: Half Placket | GI20: Cashmere | GJ20: H | GK20: Fall | GL20: Do not wash | GM20: Regular | GN20: No Elasticity | GO20: Positioning Printing | GP20: Buyer provides | GQ20: Woven | GR20: Off the Shoulder | GS20: Middle East | GT20: Size × Color | GU20: US/EU size | GV20: Alpha | GW20: M | GX20: Black | HL20: Inch | HM20: 2 | HO20: 40 | HP20: 29 | HW20: 35.5 | HX20: 37 | HY20: 27.6 | HZ20: 29.2 | IA20: 27.4 | IB20: 39 | IE20: http://www.companyname.com/images/1250.main.jpg | IF20: http://www.companyname.com/images/1250.main.jpg | IG20: http://www.companyname.com/images/1250.main.jpg | IO20: http://www.companyname.com/images/1250.main.jpg | IP20: Used - Like new | IQ20: 5 | IR20: 2.99 | IS20: 5.99 | IT20: 9.2 | IU20: 2 | IV20: 3 | IW20: 4 | IZ20: 1 Day | JA20: test1 | JB20: Imported | JC20: I will ship this item myself | JE20: No Warning Applicable
B21: 29069 | C21: Example Women T-shirt, 156 Black T-shirt | D21: EXAMPLE-156-US | E21: EXAMPLE-156-US-red-S | H21: Unleash your personal style with our classic fit tee. Crafted from 100% cotton, it offers unmatched comfort and durability. The tee features a unique, eye-catching graphic that embodies modern chic. Perfect for casual outings or layering under a jacket, this T-shirt is versatile for any occasion. With a breathable fabric that holds its shape, it's a wardrobe staple you'll reach for time and again. Make a statement and stay cozy in a shirt designed to express who you are. (Character count: 493) | I21: 100% premium cotton for ultimate comfort. | J21: Timeless design meets modern style. | K21: Durable fabric, perfect for daily wear | L21: Machine washable and easy to care for. | M21: Versatile fit for every body type. | O21: http://www.companyname.com/images/1250.main.jpg | P21: http://www.companyname.com/images/1250.main.jpg | Q21: http://www.companyname.com/images/1250.main.jpg | R21: http://www.companyname.com/images/1250.main.jpg | CO21: Recycle Polyester | DS21: Y2K | ER21: 32 | ES21: 28 | ET21: 40 | FY21: Short Length | FZ21: Yes | GA21: Long Sleeve | GB21: Raglan sleeve | GC21: No Padding | GD21: Fake Pockets | GE21: Mushroom | GF21: No | GG21: Non-Stretch | GH21: Half Placket | GI21: Cashmere | GJ21: H | GK21: Fall | GL21: Do not wash | GM21: Regular | GN21: No Elasticity | GO21: Positioning Printing | GP21: Buyer provides | GQ21: Woven | GR21: Off the Shoulder | GS21: Middle East | GT21: Size × Color | GU21: US/EU size | GV21: Alpha | GW21: S | GX21: Red | HL21: Inch | HM21: 0 | HO21: 36 | HP21: 28 | HW21: 33.9 | HX21: 35.5 | HY21: 26 | HZ21: 27.6 | IA21: 35.9 | IB21: 37.4 | IE21: http://www.companyname.com/images/1250.main.jpg | IF21: http://www.companyname.com/images/1250.main.jpg | IG21: http://www.companyname.com/images/1250.main.jpg | IO21: http://www.companyname.com/images/1250.main.jpg | IP21: Used - Like new | IQ21: 5 | IR21: 3.99 | IS21: 7.99 | IT21: 9.2 | IU21: 2 | IV21: 3 | IW21: 4 | IZ21: 1 Day | JA21: test1 | JB21: Imported | JC21: I will ship this item myself | JE21: No Warning Applicable
B22: 29069 | C22: Example Women T-shirt, 156 Black T-shirt | D22: EXAMPLE-156-US | E22: EXAMPLE-156-US-red-M | H22: Unleash your personal style with our classic fit tee. Crafted from 100% cotton, it offers unmatched comfort and durability. The tee features a unique, eye-catching graphic that embodies modern chic. Perfect for casual outings or layering under a jacket, this T-shirt is versatile for any occasion. With a breathable fabric that holds its shape, it's a wardrobe staple you'll reach for time and again. Make a statement and stay cozy in a shirt designed to express who you are. (Character count: 493) | I22: 100% premium cotton for ultimate comfort. | J22: Timeless design meets modern style. | K22: Durable fabric, perfect for daily wear | L22: Machine washable and easy to care for. | M22: Versatile fit for every body type. | O22: http://www.companyname.com/images/1250.main.jpg | P22: http://www.companyname.com/images/1250.main.jpg | Q22: http://www.companyname.com/images/1250.main.jpg | R22: http://www.companyname.com/images/1250.main.jpg | CO22: Recycle Polyester | DS22: Y2K | ER22: 32 | ES22: 28 | ET22: 40 | FY22: Short Length | FZ22: Yes | GA22: Long Sleeve | GB22: Raglan sleeve | GC22: No Padding | GD22: Fake Pockets | GE22: Mushroom | GF22: No | GG22: Non-Stretch | GH22: Half Placket | GI22: Cashmere | GJ22: H | GK22: Fall | GL22: Do not wash | GM22: Regular | GN22: No Elasticity | GO22: Positioning Printing | GP22: Buyer provides | GQ22: Woven | GR22: Off the Shoulder | GS22: Middle East | GT22: Size × Color | GU22: US/EU size | GV22: Alpha | GW22: M | GX22: Red | HL22: Inch | HM22: 2 | HO22: 40 | HP22: 29 | HW22: 35.5 | HX22: 37 | HY22: 27.6 | HZ22: 29.2 | IA22: 27.4 | IB22: 39 | IE22: http://www.companyname.com/images/1250.main.jpg | IF22: http://www.companyname.com/images/1250.main.jpg | IG22: http://www.companyname.com/images/1250.main.jpg | IO22: http://www.companyname.com/images/1250.main.jpg | IP22: Used - Like new | IQ22: 5 | IR22: 3.99 | IS22: 7.99 | IT22: 9.2 | IU22: 2 | IV22: 3 | IW22: 4 | IZ22: 1 Day | JA22: test1 | JB22: Imported | JC22: I will ship this item myself | JE22: No Warning Applicable
B23: 12408 | C23: Example reclaimed Cabinet Solid Wood with 4 Drawers | D23: EXAMPLE-576 | E23: Example_Brand Night Stand with 4 Drawers (White, 21 inch) | DL23: Wood | DQ23: Painted | DR23: Cedar | DS23: Vintage | DT23: Plug Powered | DU23: 110V (included)-240V (included) | DV23: US Plug | DZ23: Yes | EA23: Hardwood | EC23: Block Board (large Core Board) | EG23: Yes | EH23: <3.2 Cubic Feet | EI23: <27 Inches | EJ23: <30 Lbs | EK23: Without Battery | EQ23: Red | GT23: Color × Size | GY23: White | GZ23: 21 inch | IE23: http://www.companyname.com/images/1250.main.jpg | IF23: http://www.companyname.com/images/1250.main.jpg | IG23: http://www.companyname.com/images/1250.main.jpg | IO23: http://www.companyname.com/images/1250.main.jpg | IP23: Used - Very good | IQ23: 5 | IR23: 2.99 | IS23: 5.99 | IT23: 9.2 | IU23: 2 | IV23: 3 | IW23: 4 | IZ23: 1 Day | JA23: test1 | JB23: Imported | JC23: I will ship this item myself | JE23: No Warning Applicable
B24: 12408 | C24: Example reclaimed Cabinet Solid Wood with 4 Drawers | D24: EXAMPLE-576 | E24: Example_Brand Night Stand with 2 Drawers (White, 24 inch) | DL24: Wood | DQ24: Painted | DR24: Cedar | DS24: Vintage | DT24: Plug Powered | DU24: 110V (included)-240V (included) | DV24: US Plug | DZ24: Yes | EA24: Hardwood | EC24: Block Board (large Core Board) | EG24: Yes | EH24: <3.2 Cubic Feet | EI24: <27 Inches | EJ24: <30 Lbs | EK24: Without Battery | EQ24: Red | GT24: Color × Size | GY24: White | GZ24: 24 inch | IE24: http://www.companyname.com/images/1250.main.jpg | IF24: http://www.companyname.com/images/1250.main.jpg | IG24: http://www.companyname.com/images/1250.main.jpg | IO24: http://www.companyname.com/images/1250.main.jpg | IP24: Used - Very good | IQ24: 5 | IR24: 2.99 | IS24: 5.99 | IT24: 9.2 | IU24: 2 | IV24: 3 | IW24: 4 | IZ24: 1 Day | JA24: test1 | JB24: Imported | JC24: I will ship this item myself | JE24: No Warning Applicable
B25: 12408 | C25: Example reclaimed Cabinet Solid Wood with 4 Drawers | D25: EXAMPLE-576 | E25: Example_Brand Night Stand with 2 Drawers (Grey, 21 inch) | DL25: Wood | DQ25: Painted | DR25: Cedar | DS25: Vintage | DT25: Plug Powered | DU25: 110V (included)-240V (included) | DV25: US Plug | DZ25: Yes | EA25: Hardwood | EC25: Block Board (large Core Board) | EG25: Yes | EH25: <3.2 Cubic Feet | EI25: <27 Inches | EJ25: <30 Lbs | EK25: Without Battery | EQ25: Red | GT25: Color × Size | GY25: Grey | GZ25: 21 inch | IE25: http://www.companyname.com/images/1250.main.jpg | IF25: http://www.companyname.com/images/1250.main.jpg | IG25: http://www.companyname.com/images/1250.main.jpg | IO25: http://www.companyname.com/images/1250.main.jpg | IP25: Used - Very good | IQ25: 5 | IR25: 2.99 | IS25: 5.99 | IT25: 9.2 | IU25: 2 | IV25: 3 | IW25: 4 | IZ25: 1 Day | JA25: test1 | JB25: Imported | JC25: I will ship this item myself | JE25: No Warning Applicable
B26: 12408 | C26: Example reclaimed Cabinet Solid Wood with 4 Drawers | D26: EXAMPLE-576 | E26: Example_Brand Night Stand with 2 Drawers (Grey, 24 inch) | DL26: Wood | DQ26: Painted | DR26: Cedar | DS26: Vintage | DT26: Plug Powered | DU26: 110V (included)-240V (included) | DV26: US Plug | DZ26: Yes | EA26: Hardwood | EC26: Block Board (large Core Board) | EG26: Yes | EH26: <3.2 Cubic Feet | EI26: <27 Inches | EJ26: <30 Lbs | EK26: Without Battery | EQ26: Red | GT26: Color × Size | GY26: Grey | GZ26: 24 inch | IE26: http://www.companyname.com/images/1250.main.jpg | IF26: http://www.companyname.com/images/1250.main.jpg | IG26: http://www.companyname.com/images/1250.main.jpg | IO26: http://www.companyname.com/images/1250.main.jpg | IP26: Used - Very good | IQ26: 5 | IR26: 2.99 | IS26: 5.99 | IT26: 9.2 | IU26: 2 | IV26: 3 | IW26: 4 | IZ26: 1 Day | JA26: test1 | JB26: Imported | JC26: I will ship this item myself | JE26: No Warning Applicable

Sheet Data Definitions
A1: How to complete your template
A2: Group Name | B2: Field Name | C2: Local Label Name | D2: Definition and Use | E2: Accepted Values | F2: Example | G2: Required?
A3: Product Identity - These are attributes that are important to buyers and should be populated for all your items. Some are required to create an offer.
B4: t_0_category | C4: Category | D4: Only supports uploading a single category of goods. Category ID has been preset in the dropdown. | E4: Input an appropriate category. | F4: 13788 | G4: Required
B5: t_0_productname | C5: Product Name | D5: Following MMS guidelines: Maximum of 500 characters, must not contain blank lines or more than two consecutive spaces. | E5: Provide a name for the item including brand, color, fit and size,in 500 characters | F5: Robert Graham Men's Maya Bay Short Sleeve Classic Fit Shirt, Cranberry, X-Large | G5: Required
B6: t_0_contributiongoods | C6: Contribution Goods | D6: The code provided to providers for marking and managing parent product links, filled in by the merchant. Must be unique within the store. Rows with the same Contribution Goods value will be treated by the system as different child SKUs under the same parent product. Please do not use leading or trailing spaces in SKUs. | E6: This attribute indicates the SKU number as assigned by the contributor | F6: ABC123 | G6: Required
B7: t_0_contributionsku | C7: Contribution SKU | D7: The code provided by the platform to providers for marking and managing sub-product links, filled in by the merchant. Must be unique within the store.Please do not use leading or trailing spaces in SKUs. | E7: This attribute indicates the SKU number as assigned by the contributor | F7: ABC123 | G7: Required
B8: t_0_updateoradd | C8: Update or Add | D8: Specifies the type of operation ("Update": overwrite existing data; "Partial Update": modify only the entered content; "Add": create a new product) to perform on the provided data. If left blank, the default option will be "Add". Use "Update" when editing existing product information or creating a new product, and enter "Partial Update" when updating only the entered product information fields. | E8: Select one of the following options: Add, Update, PartialUpdate. | F8: Add | G8: Optional
B9: t_0_goodsid | C9: Goods Id | D9: Only when editing existing product information, fill in the Goods ID generated by temu. | G9: Optional
B10: t_0_skuid | C10: Sku Id | D10: Only when editing existing product information, fill in the SKU ID generated by temu. | G10: Optional
B11: t_0_brand | C11: Brand | D11: If the product requires brand information, please select both Brand and Trademark of that. | E11: Select the brand name of the product https://seller-eu.temu.com/performance/account-health.html?tab=compliance&opType=register | F11: Nike | G11: Optional
B12: t_0_trademark | C12: Trademark | D12: If the product requires brand information, please select both Brand and Trademark of that. Please take care when selecting the Brand and Trademark you want to associate with. | E12: Select the trademark name of the product | F12: Nike | G12: Conditionally Required
A13: Product Description - These attributes have an effect on how customers can find your product on the site using browse or search
B14: t_1_productdescription | C14: Product Description | D14: A text description of the product. | E14: Following MMS guidelines: Maximum of 2000 characters, not support the rich text formatting. | F14: Long sleeve v-neck cardigan with a ribbed waistline and pockets with bow detailing | G14: Optional
B15: t_1_bulletpoint | C15: Bullet Point | D15: Brief descriptive text, called out via a bullet point, regarding a specific aspect of the product. These display directly under or next to your product photo, it is useful to put interesting information in these fields. Bullet points will be inserted automatically. | E15: Following MMS guidelines: Maximum of 700 characters, not support the rich text formatting. You can upload one bullet point per cell | F15: Made with nourishing pure aloe vera gel | G15: Optional
B16: t_1_detailimagesurl | C16: Detail Images URL | D16: The URL for detail images of your product. These images will be shown on the detail page when the customer clicks through to see other views associated with the product. For example, you can use this field to show the label information or packaging of your product. Upload additional images with different views to the item, or with some emotional surrounding as additional image. | E16: Obtain URLs from any image hosting website and enter them into the respective cells. i. Aspect ratio: min of 1:3; ii. Width or height: min of 480px; iii. File size: max of 3MB; iv. File types: jpeg, jpg, png | F16: http://www.companyname.com/images/1250.main.jpg | G16: Optional
B17: t_1_detailvideourl | C17: Detail Video URL | D17: The URL for detail video of your product. The detail video will be presented at the top of the product details section. | E17: Obtain URLs from any image hosting website and enter them into the respective cells. i. Aspect ratio: 1:1, 4:3, 16:9 ii. Resolution: min of 720p iii. Duration: max of 180s iv. File size: max of 300MB v. File types: wmv, avi, 3gp, mov, mp4, flv, rmvb, mkv, m4v, x-flv | F17: http://www.companyname.com/videos/1250..mp4 | G17: Optional
A18: Sale Property (At Least One, At Most Two) - These attributes used for product is available in different variations
B19: t_3_variationtheme | C19: Variation Theme | D19: Describes the parameter(s) by which the parent product may vary. The value input for this field should be the same for all the SKUs of the same product. Example: If the product varies by size, input the value Size. If the product varies by color, input the value Color. Terms used for variation themes are created by you the merchant. (e.g. 'quantity' can be any number that you choose). | E19: Select and applicable variation theme. | F19: Color × Size | G19: Required
A20: Variations - These are attributes that are important to buyers and should be populated for the sku of the product
B21: t_5_skuimagesurl | C21: SKU Images URL | D21: The SKU images will be displayed at the top of the product page when the customer clicks through to see other views associated with the product. Different SKU images will form a carousel of the product. For example, you can use this field to show the label information or packaging of your product. Upload additional images with different views to the item, or with some emotional surrounding as additional image. | E21: a. For clothes: i. Aspect ratio: 3:4 ii. Width: min of 1340px iii. Height: min of 1785px iv. File size: max of 3MB v. File types: jpeg, jpg, png b. For other products: i. Aspect ratio: 1:1 ii. Width or height: min of 800px iii. File size: max of 3MB iv. File types: jpeg, jpg, png | F21: http://www.companyname.com/images/1250.main.jpg | G21: Required
B22: t_5_dimensions | C22: Dimensions | D22: Please use imperial units to indicate product dimensions. This can help buyers get a better understanding of the size and specifications of the product. | E22: a. For clothes: i. Aspect ratio: 3:4 ii. Width: min of 1340px iii. Height: min of 1785px iv. File size: max of 3MB v. File types: jpeg, jpg, png b. For other products: i. Aspect ratio: 1:1 ii. Width or height: min of 800px iii. File size: max of 3MB iv. File types: jpeg, jpg, png | F22: http://www.companyname.com/images/1250.dimension.jpg | G22: Optional
B23: t_5_condition | C23: Condition | D23: “Condition” field is used to describe the condition of used-product, including different levels of quality.Condition is required to show to the consumers to help making decisions. All SKUs in a product need to share a set of Conditons. | E23: Select an appropriate for your product.Different categories have different standards for classifying the levels of Condition. You can view it in Temu Seller Center. | F23: Used - Like new | G23: Required
B24: t_5_quantity | C24: Quantity | D24: Enter the quantity of the item you are making available for sale. This is your current INVENTORY commitment. Quantity is required for all "child" or stand-alone items. If left blank when first submitting the product information, the item will be displayed as "Out of stock." | E24: Enter the quantity of the item you are making available for sale. This is your current inventory commitment (as a whole number) | F24: 152 | G24: Required
B25: t_5_base_price_usd | C25: Base Price - USD | D25: The Base Price should reflect your costs and expected profit. You'll receive sales proceeds based on the Operative Price for each product sold. The final Retail Price is not directly linked to your payment settlement. Base price must be less than list price. | E25: The price range is $0.01-$99999999.99, with a maximum of 2 decimal points and will be rounded up. | F25: 3.99 | G25: Required
B26: t_5_list_price_usd | C26: List Price - USD | D26: The list price is the suggested or recommended retail price of a product set by the manufacturer. It must be a genuine selling price on the market and in compliance with applicable laws and regulations. If your product is listed for sale in the EU, the product must have been advertised and sold at or above the provided list price by at least one EU retailer. By inputting a list price you are confirming that: - You are not the only seller of the product on the market where the product will be sold (and where a list price comparison will be made); and - You have evidence that the list price you are providing is a genuine price at which the product is generally sold. You must make such evidence available to Temu on request. Base price must be less than list price. | E26: The price range is $0.01-$99,999,999.99, with a maximum of 2 decimal points and will be rounded up. | F26: 5.79 | G26: Required
B27: t_5_weight_lb | C27: Weight - lb | D27: This will be used to indicate the package weight of the SKU and will be used by Temu to estimate logistics costs. Please fill this in accurately. | E27: The weight range is 0.1 lb-9,999.9 lb, with a maximum of 1 decimal point, and will be rounded up. | F27: 10.2 | G27: Required
B28: t_5_length_in | C28: Length - in | D28: This will be used to indicate the package volune of the SKU and will be used by Temu to estimate logistics costs. Please fill this in accurately. | E28: The length range is 0.1 in-999.9 in, with a maximum of 1 decimal point, and will be rounded up. | F28: 3.1 | G28: Required
B29: t_5_width_in | C29: Width - in | D29: This will be used to indicate the package volune of the SKU and will be used by Temu to estimate logistics costs. Please fill this in accurately. | E29: The length range is 0.1 in-999.9 in, with a maximum of 1 decimal point, and will be rounded up. | F29: 2.1 | G29: Required
B30: t_5_height_in | C30: Height - in | D30: This will be used to indicate the package volune of the SKU and will be used by Temu to estimate logistics costs. Please fill this in accurately. | E30: The length range is 0.1 in-999.9 in, with a maximum of 1 decimal point, and will be rounded up. | F30: 1.1 | G30: Required
B31: t_5_externalproductidtype | C31: External Product ID Type | D31: The type of standard, unique identifier entered in the Product ID field. This is a required field if Product ID is provided. | E31: The type of standard, unique identifier entered in the Product ID field. This is a required field if Product ID is provided. | F31: UPC | G31: Optional
B32: t_5_externalproductid | C32: External Product ID | D32: A standard, alphanumeric string that uniquely identifies the product. This could be a GCID (16 alphanumeric characters), UPC or EAN. This is a required field if product_id_type is provided. | E32: Provide the corresponding external product id value based on the type that was selected | F32: 714532191586 | G32: Conditionally Required
A33: Offer - These attributes are required to make your product buyable for customers on the site
B34: t_6_handlingtime | C34: Handling Time | D34: Indicates the time, in days, between when you receive an order for an item and when you can ship the item. The default production time is one to two business days. Use this field if your production time is greater than two business days. | E34: The same as MMS. Only supports 1, 2 days. If left blank, the default option will be "2 Days" | F34: 1 day | G34: Optional
B35: t_6_shippingtemplate | C35: Shipping Template | D35: Sellers can create a set of ship configurations based on business needs and use cases. The ship configurations can be region based and have rules to set SLA and rate for the region. When listing product to create offer, seller needs to select one ship configuration for the product. The ship configuration will be used to retrieve the valid ship options on the website. | E35: Must first finish creating the shipping template in [https://seller-eu.temu.com/shipping-templates-create.html], and all available shipping template names in the store will be displayed here. | F35: "Free Shipping Template", "Default Template" | G35: Required
B36: t_6_importdesignation | C36: Import Designation | D36: If made in USA from imported materials select “Made in USA and Imported.” If some units are from USA and some imported select “Made in USA or Imported.” If made in USA from Mexican materials select “Made in USA.” If made outside USA, select “Imported.” | E36: Imported; Made in USA or Imported; Made in USA and Imported; Made in USA | F36: Imported; | G36: Optional
B37: t_6_fulfillmentchannel | C37: Fulfillment Channel | E37: If left blank, the default option will be "I will ship this item myself" | G37: Optional
A38: Qualifications - Attributes used to comply with consumer laws in the country or region where the item is sold
B39: t_7_productguide | C39: Product Guide | E39: Please get the URL of the manual from any image hosting website and fill it into the cell. Product Guide Filing Requirements: a. File size: max of 15MB b. File type: pdf | F39: http://www.companyname.com/guide/1250.pdf | G39: Optional
B40: t_7_Country/Region of Origin | C40: Country/Region of Origin | D40: The Country/Region of Origin of a product is generally the country or region where the product was wholly produced or manufactured. If more than one country or region is involved in the product’s production or manufacture, the Country/Region of Origin is generally where the last "substantial transformation" of the product occurred. | E40: Select the Country/Region of the product | F40: Germany | G40: Required
B41: t_7_Province of Origin | C41: Province of Origin | D41: When the country of origin is Mainland China, the province of origin cannot not be empty. | E41: Select the Province of the product | G41: Conditionally Required
B42: t_7_californiaproposition65warningtype | C42: California Proposition 65 Warning Type | D42: This attribute captures information needed from suppliers which is used to display applicable California Proposition 65 warnings on the detail page | E42: Select the warning type applicable to your product, if any. You certify that the warning provided satisfies legal requirements and that you’ll remove a warning previously provided only if it is no longer legally required. | F42: No Warning Applicable | G42: Required
B43: t_7_californiaproposition65chemicalnames | C43: California Proposition 65 Chemical Names | D43: This attribute captures information needed from suppliers which is used to display applicable California Proposition 65 warnings on the detail page | E43: If you selected the Food, Furniture, or Chemical warning you must indicate a chemical(s). You certify that the chemical(s) satisfies legal requirements and that you’ll remove a chemical previously provided only if it is no longer legally required. | F43: Abiraterone acetate | G43: Conditionally Required

Sheet Dropdown Lists
A1: t_1_Category | B1: t_973431DD2C61366DBACC56E61E132E05 | C1: 12155
A2: t_1_Product type | B2: t_CE9696B61FAB33F2B7AC38BD1A6904FE | C2: Normal product | D2: Custom product
A3: t_1_Custom product_Customization processing technique | B3: t_E596E04876A938D89430E31F12190EAE | C3: Single technique | D3: Combined techniques
A4: t_1_Custom product_Single technique_Primary technique | B4: t_210AC56516C831C3B975426026564B85 | C4: Basic technique | D4: Canvas/paper customization technique | E4: Organic material (e.g., acrylic/resin) customization technique | F4: Wood product customization technique | G4: Metal product customization technique | H4: Leather/fabric customization technique
A5: t_1_Custom product_Combined techniques_Primary technique | B5: t_5DB35C4529DB3F96BF4F53E1FEC22A97 | C5: Canvas/paper customization technique | D5: Organic material (e.g., acrylic/resin) customization technique | E5: Wood product customization technique | F5: Metal product customization technique | G5: Leather/fabric customization technique
A6: t_1_Custom product_Combined techniques_Metal product customization technique_Secondary technique | B6: t_5A2E371F897639048DDE5DABAB9B152C | C6: Laser engraving - text | D6: Laser engraving - images | E6: Mechanical engraving - text | F6: Debossing | G6: Welding | H6: UV | I6: Silk screen printing - text | J6: Silk screen printing - image | K6: Spray painting | L6: Soft enamel | M6: Laser cutting - text | N6: Laser cutting - image | O6: Rhinestone setting | P6: Electroplating
A7: t_1_Custom product_Single technique_Organic material (e.g., acrylic/resin) customization technique_Secondary technique | B7: t_6CC11CB0854138C9A2CAB6DC90AACA9A | C7: Laser engraving - text | D7: Laser engraving - images | E7: Mechanical engraving - text | F7: Debossing | G7: UV | H7: Silk screen printing - text | I7: Silk screen printing - image | J7: Laser cutting - text | K7: Laser cutting - image | L7: Hand-painted nail art
A8: t_1_Custom product_Single technique_Wood product customization technique_Secondary technique | B8: t_4BDCEE54E14C361091E3B7E7BC6BFA58 | C8: Laser engraving - text | D8: Laser engraving - images | E8: Mechanical engraving - text | F8: Debossing
A9: t_1_Custom product_Combined techniques_Organic material (e.g., acrylic/resin) customization technique_Secondary technique | B9: t_4E8EB62C344D3136894C37789B634AC8 | C9: Laser engraving - text | D9: Laser engraving - images | E9: Mechanical engraving - text | F9: Debossing | G9: UV | H9: Silk screen printing - text | I9: Silk screen printing - image | J9: Laser cutting - text | K9: Laser cutting - image
A10: t_1_Custom product_Single technique_Canvas/paper customization technique_Secondary technique | B10: t_B0B8A13405AC332B85C28D653BD74B34 | C10: Hand-painting - sketch | D10: Hand-painting - watercolor | E10: Hand-painting - oil painting | F10: Hand-painting - printmaking | G10: Hand-painting - comic | H10: Debossing
A11: t_1_Custom product_Single technique_Metal product customization technique_Secondary technique | B11: t_BA7DD3CAEAAF3F6C820F178068C1218E | C11: Laser engraving - text | D11: Laser engraving - images | E11: Mechanical engraving - text | F11: Debossing | G11: Welding | H11: Etching | I11: UV | J11: Silk screen printing - text | K11: Silk screen printing - image | L11: Spray painting | M11: Soft enamel | N11: Epoxy - text | O11: Epoxy - images | P11: Laser cutting - text | Q11: Laser cutting - image | R11: Rhinestone setting | S11: Electroplating
A12: t_1_Custom product_Combined techniques_Canvas/paper customization technique_Secondary technique | B12: t_4D36BB0BF9A633DDA10597E97D2DE70D | C12: Silk screen printing - text | D12: Silk screen printing - image | E12: Hot stamping - text | F12: Hot stamping - image | G12: Debossing
A13: t_1_Custom product_Combined techniques_Leather/fabric customization technique_Secondary technique | B13: t_B8ED491BA39F3348BAC02EDEAF8D3E6A | C13: Laser engraving - text | D13: Laser engraving - images | E13: UV | F13: Silk screen printing - text | G13: Silk screen printing - image | H13: Soft enamel | I13: Hot stamping - text | J13: Hot stamping - image | K13: Debossing
A14: t_1_Custom product_Single technique_Leather/fabric customization technique_Secondary technique | B14: t_82B46A7862C13CCC82AB8265B43CD5D1 | C14: Laser engraving - text | D14: Laser engraving - images | E14: UV | F14: Silk screen printing - text | G14: Silk screen printing - image | H14: Soft enamel | I14: Epoxy - text | J14: Epoxy - images | K14: Hot stamping - text | L14: Hot stamping - image | M14: Tin stamping | N14: Heat transfer printing - text | O14: Heat transfer printing - image | P14: Embroidery | Q14: Flocking | R14: Heat press printing - text | S14: Heat press printing - image | T14: Digital printing | U14: Debossing | V14: Woven pattern - adhesive patch
A15: t_1_Custom product_Combined techniques_Wood product customization technique_Secondary technique | B15: t_102B0F8B23393DE98AFB27DE3D742D48 | C15: Laser engraving - text | D15: Laser engraving - images | E15: Mechanical engraving - text | F15: Debossing
A16: t_1_Update or Add | B16: t_59D4DF059C473EBE9972B0D6D3C6BFD5 | C16: Update | D16: PartialUpdate | E16: Add
A17: t_1_Brand | B17: t_BCE822F8514631DFAA900D604C1FA3AD | C17: Must first finish adding the brand in [https://seller.temu.com/brands-property.html], and all available brand names of the store will be displayed here.
A18: t_3_12155_19 - Style | B18: t_24E9F6E5671238AEB940988128184600 | C18: Vintage | D18: Boho | E18: Glam | F18: Classic | G18: Contemporary | H18: Traditional | I18: International | J18: Cape Cod | K18: Rustic | L18: French country | M18: Lodge | N18: Mediterranean | O18: Shabby Chic | P18: Southwestern | Q18: Garden | R18: Tropical | S18: Art deco | T18: Modern | U18: Eclectic | V18: Asian | W18: Moroccan | X18: Scandinavian | Y18: Colonial | Z18: English | AA18: French | AB18: Italian | AC18: Mission | AD18: Old World | AE18: Shaker | AF18: Victorian | AG18: Latin | AH18: Chinese | AI18: Japanese | AJ18: Antique | AK18: Baroque | AL18: Coastal | AM18: Industrial | AN18: Tiffany | AO18: Mid-century modern | AP18: Transitional | AQ18: Farmhouse | AR18: Americana | AS18: European | AT18: Nautical | AU18: Italian | AV18: Country rustic
A19: t_3_12155_423 - Holidays | B19: t_94E247C1F859327C9FBF193DB3EE8752 | C19: Christmas | D19: Halloween | E19: Easter | F19: Hanukkah | G19: Thanksgiving | H19: St. Patrick's Day | I19: Valentine's Day | J19: Ramadan (Eid Al-Fitr) | K19: Father's Day | L19: Mother's Day | M19: Graduation | N19: Juneteenth | O19: 4th of July | P19: Oktoberfest | Q19: Day of the Dead | R19: Diwali | S19: Memorial Day | T19: Saint Nicholas Day | U19: Kwanzaa | V19: Labor Day | W19: Grandparents Day | X19: Earth Day | Y19: Purim | Z19: St. Patrick's Day | AA19: National Freedom Day | AB19: Groundhog Day | AC19: National Wear Red Day | AD19: Palm Sunday | AE19: Lei Day | AF19: Cinco de Mayo | AG19: National Nurses Day | AH19: Eid ul Adha | AI19: French National Day | AJ19: Muharram/Islamic New Year | AK19: National Aviation Day | AL19: National Grandparents Day | AM19: St. Nicholas Day
A20: t_3_12155_127 - Mounting Type | B20: t_12264466A77D3B36AC2DAA034A1A5FE2 | C20: Wall hanging | D20: Door mount | E20: Tabletop | F20: Pole Mount | G20: Stand mount
A21: t_3_12155_121 - Material | B21: t_A6BF6E6B85CF3C52B1B5A315BF020790 | C21: Glass | D21: Suede | E21: Plastic | F21: Wood | G21: Vinyl | H21: Leather | I21: Ceramic | J21: Wicker | K21: Manufactured wood | L21: Aluminum | M21: Stainless Steel | N21: Pewter | O21: Acrylic | P21: Resin | Q21: Rattan | R21: Iron | S21: Porcelain | T21: Bamboo | U21: Crystal | V21: Stone | W21: Abs (acrylonitrile Butadiene Styrene) | X21: Polyethylene | Y21: Polyurethane (pu) | Z21: PET (polyethylene Terephthalate) | AA21: Terracotta | AB21: Melamine | AC21: PC (Polycarbonate) | AD21: PS (polystyrene) | AE21: Tritan | AF21: enamel | AG21: wheat straw | AH21: Plant | AI21: Pampas Grass | AJ21: Log | AK21: Genuine Leather | AL21: Rubber | AM21: PE
A22: t_3_12155_130 - Theme | B22: t_01BA699F340E3B1C80CC2D963BF4E23C | C22: Animals | D22: Military | E22: Flowers | F22: Insects | G22: Plants | H22: Religious | I22: Family | J22: Reptiles | K22: Schools | L22: Seascape | M22: Bird | N22: Heart | O22: Nautical | P22: Pop culture | Q22: Pastoral-themes | R22: Angels | S22: Buildings | T22: Dinosaurs | U22: Gargoyles | V22: Celestial-symbols | W22: Romance | X22: Teddy-bears | Y22: Christian-crosses | Z22: Candy-canes | AA22: Elves | AB22: Santa-claus | AC22: Nativity-theme | AD22: Christmas-nutcrackers | AE22: Snowmen | AF22: Snow-sleds | AG22: Stars | AH22: Trains | AI22: Christmas-stockings | AJ22: Wedding | AK22: Bears | AL22: Christmas-gingerbread-houses | AM22: Cats | AN22: Dogs | AO22: Deer | AP22: Elephants | AQ22: Giraffes | AR22: Foxes | AS22: Primates | AT22: Koalas | AU22: Horses | AV22: Kangaroos | AW22: Rodents | AX22: Rabbits | AY22: Otters | AZ22: Skunks | BA22: Raccoons | BB22: Wolves | BC22: Zebras | BD22: Hippopotamuses | BE22: Rhinoceroses | BF22: Moose | BG22: Elk | BH22: Amphibians | BI22: Carnivals | BJ22: Turtles | BK22: Clowns | BL22: Churches | BM22: Urban | BN22: Retail-shops | BO22: Gourmet-food | BP22: Wine | BQ22: Restaurants | BR22: Landscape | BS22: Vegetables-produce | BT22: Fruit-produce | BU22: Christmas Tree | BV22: Colleges-and-universities | BW22: Inspirational | BX22: Christmas-wreaths | BY22: Christmas-gingerbread-men
A23: t_3_12155_2232 - Whether There Are Feathers | B23: t_64240C1C393039E6BC9AFC17C975D798 | C23: Yes | D23: No
A24: t_3_12155_Yes_2233 - Feather Material | B24: t_4FCF4D5E513C3C149F22DA945CD3A4F9 | C24: Duck Feather | D24: Goose Feather | E24: Turkey Feathers | F24: Blue Peacock Feather | G24: Artificial Feather | H24: Ostrich Feather | I24: Chicken Feather
A25: t_3_12155_1561 - Power Supply | B25: t_4D0B0322FE473E23B6C86F1C3A06BA2B | C25: Dry Battery Power | D25: Use Without Electricity | E25: Plug Powered | F25: Solar Charging | G25: USB Powered | H25: Hard-Wired | I25: USB Charging (built-in Battery) | J25: DC Power Supply
A26: t_3_12155_Hard-Wired_1132 - Operating Voltage | B26: t_E95F6272D49237EC85058109FFEB1885 | C26: 110V (included)-240V (included) | D26: 110V | E26: 120V | F26: 130V | G26: 125V
A27: t_3_12155_USB Powered_1132 - Operating Voltage | B27: t_A92A044DB98330ABAC8A9BFF0EAF7C94 | C27: ≤36V
A28: t_3_12155_DC Power Supply_1132 - Operating Voltage | B28: t_B86387DA208438EC8CA12912F5FFAD1F | C28: ≤36V
A29: t_3_12155_Plug Powered_1132 - Operating Voltage | B29: t_548CA8DB852B3D74B0E67F20F3C16269 | C29: 110V (included)-240V (included) | D29: 110V | E29: 120V | F29: 110V (included)-130V (included) | G29: 130V | H29: 125V | I29: 100V (inclusive)-127V (inclusive) | J29: 110V (inclusive)-127V (inclusive)
A30: t_3_12155_Dry Battery Power_1562 - Battery Quantity | B30: t_3210EDB3F0FF3AABAF0449B028E64379 | C30: 1 Piece | D30: 2 Pieces | E30: 3 Pieces | F30: 4 Pieces | G30: 5 Pieces | H30: 6 Pieces | I30: 7 Pieces | J30: 8 Pieces
A31: t_3_12155_Dry Battery Power_137 - Battery Type | B31: t_C0DF8857237A318CA747C05833FD5DAA | C31: 3.6V Rechargeable Li-ion Button Battery | D31: 3V Rechargeable Li-ion Button Battery | E31: Other (non-rechargeable) | F31: 3V Lithium Manganese Button Battery | G31: 1.5V Alkaline Zinc Manganese Button Battery | H31: AA Battery | I31: Button Battery (Diameter≥20mm) | J31: AAA Battery | K31: Button Battery (Diameter＜20mm)
A32: t_3_12155_Dry Battery Power_1563 - Battery Included or Not | B32: t_E59005765B61333EBCA104D04EE89C6E | C32: No | D32: Yes
A33: t_3_12155_Plug Powered_1485 - Plug Type | B33: t_9565510F9A323040988289F4033E975E | C33: US Plug
A34: t_3_12155_USB Charging (built-in Battery)_2147 - Rechargeable Battery | B34: t_752F0D87916F3F26BD65FD910E139BF9 | C34: Nickel Battery | D34: Lithium Battery
A35: t_3_12155_Solar Charging_2154 - Solar Battery Type | B35: t_0F3F86297DFD333C9666B531B0353B3C | C35: Lithium Battery | D35: Nickel Battery
A36: t_3_12155_Dry Battery Power_111 - Batteries Included | B36: t_DCB77F94B70932AA8BDCE7D9F80E8CE8 | C36: Yes | D36: No
A37: t_3_12155_2028 - Battery Capacity (mAh) - unit | B37: t_5848D61FB8923C738935B53104584AF7 | C37: MAh
A38: t_3_12155_3673 - Language Type | B38: t_DEFB38082C6A31A5849C1D6F8F18F710 | C38: English | D38: German | E38: French | F38: Spanish | G38: Japanese | H38: Korean | I38: Arabic | J38: Portuguese | K38: Italian | L38: Other Languages | M38: No Language | N38: Spanish | O38: Dutch | P38: Polish | Q38: Swedish | R38: Russian | S38: Thai | T38: Malay | U38: Romanian | V38: Greek | W38: Turkish
A39: t_3_12155_7644 - Does It Contain Real Plants? | B39: t_8B27CDF0B6B737EE95B70861C649A6C1 | C39: yes | D39: No
A40: t_4_12155_Variation Theme | B40: t_DF3583225D6B302CBD470C48973D51D7 | C40: Hair Length × Model | D40: Composition × Style | E40: Hair Length × Size | F40: Flavors × Quantity | G40: Size | H40: Quantity × Style | I40: Applicable People × Weight | J40: Color × Model | K40: Applicable People × Material | L40: Capacity × Model | M40: Flavors × Model | N40: Capacity | O40: Model × Quantity | P40: Items | Q40: Material × Style | R40: Model × Size | S40: Applicable People × Model | T40: Applicable People × Size | U40: Color × Material | V40: Capacity × Items | W40: Items × Model | X40: Color | Y40: Color × Style | Z40: Material × Quantity | AA40: Flavors × Weight | AB40: Weight | AC40: Color × Quantity | AD40: Capacity × Hair Length | AE40: Composition × Size | AF40: Applicable People × Color | AG40: Material × Size | AH40: Flavors | AI40: Items × Weight | AJ40: Hair Length × Material | AK40: Hair Length × Quantity | AL40: Applicable People × Flavors | AM40: Flavors × Material | AN40: Capacity × Style | AO40: Applicable People × Quantity | AP40: Quantity × Weight | AQ40: Size × Style | AR40: Flavors × Style | AS40: Applicable People | AT40: Capacity × Weight | AU40: Color × Items | AV40: Capacity × Flavors | AW40: Composition × Hair Length | AX40: Hair Length × Items | AY40: Size × Weight | AZ40: Hair Length × Style | BA40: Quantity × Size | BB40: Color × Flavors | BC40: Style | BD40: Color × Hair Length | BE40: Composition × Weight | BF40: Applicable People × Hair Length | BG40: Hair Length | BH40: Composition | BI40: Applicable People × Capacity | BJ40: Composition × Items | BK40: Items × Quantity | BL40: Flavors × Items | BM40: Flavors × Size | BN40: Quantity | BO40: Material | BP40: Capacity × Color | BQ40: Capacity × Material | BR40: Items × Size | BS40: Capacity × Quantity | BT40: Style × Weight | BU40: Composition × Quantity | BV40: Items × Material | BW40: Capacity × Composition | BX40: Color × Weight | BY40: Color × Size | BZ40: Hair Length × Weight | CA40: Applicable People × Composition | CB40: Material × Weight | CC40: Model × Weight | CD40: Applicable People × Items | CE40: Color × Composition | CF40: Composition × Model | CG40: Model × Style | CH40: Composition × Flavors | CI40: Flavors × Hair Length | CJ40: Items × Style | CK40: Composition × Material | CL40: Model | CM40: Material × Model | CN40: Applicable People × Style | CO40: Capacity × Size
A41: t_6_SKU type | B41: t_B6DA4BC53E3232BAA649F8D435D5D8ED | C41: Single set | D41: Multi-piece set | E41: Mixed set of different specifications | F41: Mixed set of different products
A42: t_6_Individually packed | B42: t_1AE68FAE4C233AF2AAD93B3EC17512F8 | C42: No | D42: Yes
A43: t_6_Packaging unit | B43: t_615B0E7B83663D5EBC73B2FD2EA94590 | C43: piece | D43: pair | E43: pack
A44: t_6_Item unit | B44: t_F8B5E6645AFF3F588C988B7E937238F9 | C44: piece | D44: pair | E44: pack
A45: t_6_Net content unit | B45: t_91C5EFECD78A37B3AA06432B957057FE | C45: oz | D45: lb | E45: kg | F45: g | G45: fl oz | H45: gal | I45: ml | J45: l | K45: m³ | L45: ft | M45: in | N45: m | O45: cm | P45: mm | Q45: sq ft | R45: m² | S45: sq in | T45: mm² | U45: cm² | V45: count
A46: t_6_12155_External Product ID Type | B46: t_241370342FE93115B86141B16F0D66B3 | C46: EAN | D46: UPC | E46: ISBN | F46: GTIN-14
A47: t_7_Shipping Template | B47: t_1CFBAFB02535396A90C8042DFA8BC3FD | C47: Shipping
A48: t_7_Normal product___Handling Time | B48: t_EECB1E111E013BF4A300609EE17635B6 | C48: 1 Day | D48: 2 Days
A49: t_7_Custom product_Combined techniques_Organic material (e.g., acrylic/resin) customization technique_Handling Time | B49: t_041CCA92EE77300983BA260D5471D2F6 | C49: 1 Day | D49: 2 Days | E49: 3 Days | F49: 4 Days | G49: 5 Days | H49: 6 Days | I49: 7 Days
A50: t_7_Custom product_Single technique_Canvas/paper customization technique_Handling Time | B50: t_6E3CCC98B72D3A47BE79B3E8DCF9919D | C50: 1 Day | D50: 2 Days | E50: 3 Days | F50: 4 Days | G50: 5 Days
A51: t_7_Custom product_Single technique_Organic material (e.g., acrylic/resin) customization technique_Handling Time | B51: t_275F523CC3DA36BF82F6D13DA3C4DE73 | C51: 1 Day | D51: 2 Days | E51: 3 Days | F51: 4 Days | G51: 5 Days
A52: t_7_Custom product_Combined techniques_Leather/fabric customization technique_Handling Time | B52: t_358C61997BEA39239CE0596AA5F8E1FD | C52: 1 Day | D52: 2 Days | E52: 3 Days | F52: 4 Days | G52: 5 Days | H52: 6 Days | I52: 7 Days
A53: t_7_Custom product_Single technique_Wood product customization technique_Handling Time | B53: t_E2BBEA22FEC83C4ABFC3ECA4B013CCBA | C53: 1 Day | D53: 2 Days | E53: 3 Days | F53: 4 Days | G53: 5 Days
A54: t_7_Custom product_Single technique_Basic technique_Handling Time | B54: t_012109DDB92E37C782942343C3FAA646 | C54: 1 Day | D54: 2 Days | E54: 3 Days
A55: t_7_Handling Time | B55: t_1636BD1CFBD53CA59961F2B345D4FEEB | C55: 1 Day | D55: 2 Days
A56: t_7_Custom product_Combined techniques_Wood product customization technique_Handling Time | B56: t_0BBD854D7BD33808B617FC1FB91FF644 | C56: 1 Day | D56: 2 Days | E56: 3 Days | F56: 4 Days | G56: 5 Days | H56: 6 Days | I56: 7 Days
A57: t_7_Custom product_Combined techniques_Metal product customization technique_Handling Time | B57: t_3F8AAC6653D43B55B905228704037B79 | C57: 1 Day | D57: 2 Days | E57: 3 Days | F57: 4 Days | G57: 5 Days | H57: 6 Days | I57: 7 Days
A58: t_7_Custom product_Single technique_Leather/fabric customization technique_Handling Time | B58: t_A5BB76FD41263FA5B2B1BE5B938D946D | C58: 1 Day | D58: 2 Days | E58: 3 Days | F58: 4 Days | G58: 5 Days
A59: t_7_Custom product_Single technique_Metal product customization technique_Handling Time | B59: t_35F193C6A7E13FE09ED9BAE2922D841A | C59: 1 Day | D59: 2 Days | E59: 3 Days | F59: 4 Days | G59: 5 Days
A60: t_7____Handling Time | B60: t_B08556E1743931A8BB43D554958CBDF2 | C60: 1 Day | D60: 2 Days
A61: t_7_Custom product_Combined techniques_Canvas/paper customization technique_Handling Time | B61: t_E5A9C3716EB836E7B0B213AB53232DC4 | C61: 1 Day | D61: 2 Days | E61: 3 Days | F61: 4 Days | G61: 5 Days | H61: 6 Days | I61: 7 Days
A62: t_7_Custom product___Handling Time | B62: t_A3A49CFA8D903B4794D52E7062D12F56 | C62: 1 Day | D62: 2 Days | E62: 3 Days
A63: t_7_Import Designation | B63: t_4E6356A2F95E3E55B9B8EF4AFCA2B468 | C63: Imported | D63: Made in the USA | E63: Made in the USA and Imported | F63: Made in the USA or Imported
A64: t_7_Fulfillment Channel | B64: t_7E17F961182E3936A934902E20106CAB | C64: I will ship this item myself
A65: t_8_12155_Country/Region of Origin | B65: t_1DEE4A266E48377DA726E10015B5D56F | C65: Afghanistan | D65: Albania | E65: Algeria | F65: Andorra | G65: Angola | H65: Anguilla | I65: Antigua and Barbuda | J65: Argentina | K65: Armenia | L65: Aruba | M65: Australia | N65: Austria | O65: Azerbaijan | P65: Bahamas | Q65: Bahrain | R65: Bangladesh | S65: Barbados | T65: Belarus | U65: Belgium | V65: Belize | W65: Benin | X65: Bermuda | Y65: Bhutan | Z65: Bolivia | AA65: Bosnia and Herzegovina | AB65: Botswana | AC65: Bouvet Island | AD65: Brazil | AE65: British Indian Ocean Territory | AF65: Brunei Darussalam | AG65: Bulgaria | AH65: Burkina Faso | AI65: Burundi | AJ65: Cambodia | AK65: Cameroon | AL65: Canada | AM65: Cape Verde | AN65: Cayman Islands | AO65: Central African Republic | AP65: Chad | AQ65: Chile | AR65: Mainland China | AS65: Christmas Island | AT65: Colombia | AU65: Comoros | AV65: Congo | AW65: Cook Islands | AX65: Costa Rica | AY65: Croatia | AZ65: Cuba | BA65: Cyprus | BB65: Czech Republic | BC65: Denmark | BD65: Djibouti | BE65: Dominica | BF65: Dominican Republic | BG65: East Timor | BH65: Ecuador | BI65: Egypt | BJ65: El Salvador | BK65: Equatorial Guinea | BL65: Eritrea | BM65: Estonia | BN65: Ethiopia | BO65: Faroe Islands | BP65: Fiji | BQ65: Finland | BR65: France | BS65: French Guiana | BT65: French Polynesia | BU65: French Southern Territories | BV65: Gabon | BW65: Gambia | BX65: Georgia | BY65: Germany | BZ65: Ghana | CA65: Gibraltar | CB65: Greece | CC65: Greenland | CD65: Grenada | CE65: Guadeloupe | CF65: Guam | CG65: Guatemala | CH65: Guinea | CI65: Guinea-Bissau | CJ65: Guyana | CK65: Haiti | CL65: Honduras | CM65: HK | CN65: Hungary | CO65: Iceland | CP65: India | CQ65: Indonesia | CR65: Iran | CS65: Iraq | CT65: Ireland | CU65: Israel | CV65: Italy | CW65: Jamaica | CX65: Japan | CY65: Jordan | CZ65: Kazakhstan | DA65: Kenya | DB65: Kiribati | DC65: Kosovo | DD65: Kuwait | DE65: Kyrgyzstan | DF65: Lao People's Democratic Republic | DG65: Latvia | DH65: Lebanon | DI65: Lesotho | DJ65: Liberia | DK65: Liechtenstein | DL65: Lithuania | DM65: Luxembourg | DN65: MO | DO65: Madagascar | DP65: Malawi | DQ65: Malaysia | DR65: Maldives | DS65: Mali | DT65: Malta | DU65: Marshall Islands | DV65: Martinique | DW65: Mauritania | DX65: Mauritius | DY65: Mayotte | DZ65: Mexico | EA65: Micronesia | EB65: Moldova | EC65: Monaco | ED65: Mongolia | EE65: Montenegro | EF65: Montserrat | EG65: Morocco | EH65: Mozambique | EI65: Myanmar | EJ65: Namibia | EK65: Nauru | EL65: Nepal | EM65: Netherlands | EN65: Netherlands Antilles | EO65: New Caledonia | EP65: New Zealand | EQ65: Nicaragua | ER65: Niger | ES65: Nigeria | ET65: Niue | EU65: Norfolk Island | EV65: North Korea | EW65: North Macedonia | EX65: Northern Mariana Islands | EY65: Norway | EZ65: Oman | FA65: Pakistan | FB65: Palau | FC65: Palestine | FD65: Panama | FE65: Papua New Guinea | FF65: Paraguay | FG65: Peru | FH65: Philippines | FI65: Pitcairn | FJ65: Poland | FK65: Portugal | FL65: Puerto Rico | FM65: Qatar | FN65: Republic of Korea | FO65: Reunion | FP65: Romania | FQ65: Russian Federation | FR65: Rwanda | FS65: Saint Lucia | FT65: Samoa | FU65: San Marino | FV65: Sao Tome and Principe | FW65: Saudi Arabia | FX65: Senegal | FY65: Serbia | FZ65: Seychelles | GA65: Sierra Leone | GB65: Singapore | GC65: Slovakia (Slovak Republic) | GD65: Slovenia | GE65: Solomon Islands | GF65: Somalia | GG65: South Africa | GH65: Spain | GI65: Sri Lanka | GJ65: Sudan | GK65: Suriname | GL65: Swaziland | GM65: Sweden | GN65: Switzerland | GO65: Syrian Arab Republic | GP65: TW | GQ65: Tajikistan | GR65: Tanzania | GS65: Thailand | GT65: Togo | GU65: Tokelau | GV65: Tonga | GW65: Trinidad and Tobago | GX65: Tunisia | GY65: Türkiye | GZ65: Turkmenistan | HA65: Turks and Caicos Islands | HB65: Tuvalu | HC65: Uganda | HD65: Ukraine | HE65: United Arab Emirates | HF65: United Kingdom | HG65: United States | HH65: Uruguay | HI65: Uzbekistan | HJ65: Vanuatu | HK65: Vatican City State (Holy See) | HL65: Venezuela | HM65: Vietnam | HN65: Virgin Islands (British) | HO65: Virgin Islands (U.S.) | HP65: Wallis And Futuna Islands | HQ65: Western Sahara | HR65: Yemen | HS65: Yugoslavia | HT65: Zambia | HU65: Zimbabwe
A66: t_8_Mainland China_Province of Origin | B66: t_B5D7D1D4DF403973BD97469C6D391A76 | C66: Beijing | D66: Shanghai | E66: Tianjin | F66: Chongqing | G66: Hebei | H66: Shanxi | I66: Liaoning | J66: Jilin | K66: Heilongjiang | L66: Jiangsu | M66: Zhejiang | N66: Anhui | O66: Fujian | P66: Jiangxi | Q66: Shandong | R66: Henan | S66: Hubei | T66: Hunan | U66: Guangdong | V66: Hainan | W66: Sichuan | X66: Guizhou | Y66: Yunnan | Z66: Shaanxi | AA66: Gansu | AB66: Qinghai | AC66: Inner Mongolia | AD66: Guangxi | AE66: Xizang | AF66: Ningxia | AG66: Xinjiang
A67: t_8_12155_California Proposition 65 Warning Type | B67: t_F7EEB1FA85993BFF9C65E0C87A2E7D07 | C67: Chemical | D67: Food | E67: Furniture | F67: Alcoholic Beverage | G67: Passenger or Off Road Vehicle | H67: On Product Cancer | I67: On Product Combined Cancer Reproductive | J67: On Product Reproductive | K67: No Warning Applicable | L67: Diesel Engines
A68: t_8_12155_California Proposition 65 Chemical Names | B68: t_395E9262634839C383597E24E1E36964 | C68: A-alpha-C (2-Amino-9H-pyrido[2,3-b]indole) | D68: Abiraterone acetate | E68: Acetaldehyde | F68: Acetamide | G68: Acetazolamide | H68: Acetochlor | I68: Acetohydroxamic acid | J68: 2-Acetylaminofluorene | K68: Acifluorfen sodium | L68: Acrylamide | M68: Acrylonitrile | N68: Actinomycin D | O68: AF-2;[2-(2-furyl)-3-(5-nitro-2-furyl)]acrylamide | P68: Aflatoxins | Q68: Alachlor | R68: Alcoholic beverages | S68: Alcoholic beverages, when associated with alcohol abuse | T68: Aldrin | U68: All-trans retinoic acid | V68: Aloe vera, non-decolorized whole leaf extract | W68: Alprazolam | X68: Altretamine | Y68: Amantadine hydrochloride | Z68: Amikacin sulfate | AA68: 2-Aminoanthraquinone | AB68: p-Aminoazobenzene | AC68: o-Aminoazotoluene | AD68: 4-Aminobiphenyl (4-aminodiphenyl) | AE68: 2-Amino-4-chlorophenol | AF68: 1-Amino-2,4-dibromoanthraquinone | AG68: 3-Amino-9-ethylcarbazole hydrochloride | AH68: 2-Aminofluorene | AI68: Aminoglutethimide | AJ68: Aminoglycosides | AK68: 1-Amino-2-methylanthraquinone | AL68: 2-Amino-5-(5-nitro-2-furyl)-1,3,4-thiadiazole | AM68: 4-Amino-2-nitrophenol | AN68: Aminopterin | AO68: Amiodarone hydrochloride | AP68: Amitraz | AQ68: Amitrole | AR68: Amoxapine | AS68: Amsacrine | AT68: Anabolic steroids | AU68: Analgesic mixtures containing Phenacetin | AV68: Androstenedione | AW68: Angiotensin converting enzyme (ACE) inhibitors | AX68: Aniline | AY68: Aniline hydrochloride | AZ68: o-Anisidine | BA68: o-Anisidine hydrochloride | BB68: Anisindione | BC68: Anthracene | BD68: Anthraquinone | BE68: Antimony oxide (Antimony trioxide) | BF68: Aramite | BG68: Areca nut | BH68: Aristolochic acids | BI68: Arsenic (inorganic arsenic compounds) | BJ68: Arsenic (inorganic oxides) | BK68: Asbestos | BL68: Aspirin (NOTE: It is especially important not to use aspirin during the last three months of pregnancy, unless specifically directed to do so by a physician because it may cause problems in the unborn child or complications during delivery.) | BM68: Atenolol | BN68: Atrazine | BO68: Auramine | BP68: Auranofin | BQ68: Avermectin B1 (Abamectin) | BR68: Azacitidine | BS68: Azaserine | BT68: Azathioprine | BU68: Azobenzene | BV68: Barbiturates | BW68: Beclomethasone dipropionate | BX68: Benomyl | BY68: Benthiavalicarb-isopropyl | BZ68: Benz[a]anthracene | CA68: Benzene | CB68: Benzidine [and its salts] | CC68: Benzidine-based dyes | CD68: Benzodiazepines | CE68: Benzo[b]fluoranthene | CF68: Benzo[j]fluoranthene | CG68: Benzo[k]fluoranthene | CH68: Benzofuran | CI68: Benzophenone | CJ68: Benzo[a]pyrene | CK68: Benzotrichloride | CL68: Benzphetamine hydrochloride | CM68: Benzyl chloride | CN68: Benzyl violet 4B | CO68: Beryllium and beryllium compounds | CP68: Beryllium | CQ68: Beryllium oxide | CR68: Beryllium sulfate | CS68: Betel quid with tobacco | CT68: Betel quid without tobacco | CU68: Bevacizumab | CV68: 2,2-Bis(bromomethyl)-1,3-propanediol | CW68: Bis(2-chloroethyl)ether | CX68: N,N-Bis(2-chloroethyl)-2-naphthylamine (Chlornapazine) | CY68: Bischloroethyl nitrosourea (BCNU) (Carmustine) | CZ68: Bis(chloromethyl)ether | DA68: Bis(2-chloro-1-methylethyl)ether, technical grade | DB68: Bisphenol A (BPA) | DC68: Bitumens, extracts of steam-refined and air refined | DD68: Bracken fern | DE68: Bromacil lithium salt | DF68: Bromate | DG68: Bromochloroacetic acid | DH68: 1-Bromo-3-chloropropane | DI68: Bromodichloroacetic acid | DJ68: Bromodichloromethane | DK68: Bromoethane | DL68: Bromoform | DM68: 1-Bromopropane (1-BP) | DN68: 2-Bromopropane (2-BP) | DO68: Bromoxynil | DP68: Bromoxynil octanoate | DQ68: Butabarbital sodium | DR68: 1,3-Butadiene | DS68: 1,4-Butanediol dimethanesulfonate (Busulfan) | DT68: Butylated hydroxyanisole | DU68: Butyl benzyl phthalate (BBP) | DV68: 1-Butyl glycidyl ether | DW68: beta-Butyrolactone | DX68: Cacodylic acid | DY68: Cadmium | DZ68: Cadmium and cadmium compounds | EA68: Cannabis (marijuana) smoke | EB68: Caffeic acid | EC68: Captafol | ED68: Captan | EE68: Carbamazepine | EF68: Carbaryl | EG68: Carbazole | EH68: Carbon black (airborne, unbound particles of respirable size) | EI68: Carbon-black extracts | EJ68: Carbon disulfide | EK68: Carbon monoxide | EL68: Carbon tetrachloride | EM68: Carboplatin | EN68: N-Carboxymethyl-N-nitrosourea | EO68: Catechol | EP68: Ceramic fibers (airborne particles of respirable size) | EQ68: Certain combined chemotherapy for lymphomas | ER68: Chenodiol | ES68: Chloral | ET68: Chloral hydrate | EU68: Chlorambucil | EV68: Chloramphenicol sodium succinate | EW68: Chlorcyclizine hydrochloride | EX68: Chlordane | EY68: Chlordecone (Kepone) | EZ68: Chlordiazepoxide | FA68: Chlordiazepoxide hydrochloride | FB68: Chlordimeform | FC68: Chlorendic acid | FD68: Chlorinated paraffins (Average chain length, C12;approximately 60 percent chlorine by weight) | FE68: p-Chloroaniline | FF68: p-Chloroaniline hydrochloride | FG68: Chloroethane (Ethyl chloride) | FH68: 1-(2-Chloroethyl)-3-cyclohexyl-1-nitrosourea (CCNU) (Lomustine) | FI68: 1-(2-Chloroethyl)-3-(4-methylcyclohexyl)-1-nitrosourea (Methyl-CCNU) | FJ68: Chloroform | FK68: Chloromethyl methyl ether (technical grade) | FL68: 3-Chloro-2-methylpropene | FM68: 1-Chloro-4-nitrobenzene | FN68: 2-Chloronitrobenzene | FO68: 4-Chloro-o-phenylenediamine | FP68: Chloroprene | FQ68: 2-Chloropropionic acid | FR68: Chlorothalonil | FS68: p-Chloro-o-toluidine | FT68: p-Chloro-o-toluidine, strong acid salts of | FU68: p-Chloro-o-toluidine, hydrochloride | FV68: 5-Chloro-o-toluidine and its strong acid salts | FW68: Chlorotrianisene | FX68: p-chloro-α,α,α-trifluorotoluene (para-Chlorobenzotrifluoride, PCBTF) | FY68: Chlorozotocin | FZ68: Chlorpyrifos | GA68: Chromium (hexavalent compounds) | GB68: Chrysene | GC68: C.I. Acid Red 114 | GD68: C.I. Basic Red 9 monohydrochloride | GE68: C.I. Direct Blue 15 | GF68: C.I. Direct Blue 218 | GG68: C.I. Disperse Yellow 3 | GH68: C.I. Solvent Yellow 14 | GI68: Ciclosporin (Cyclosporin A; Cyclosporine) | GJ68: Cidofovir | GK68: Cinnamyl anthranilate | GL68: Cisplatin | GM68: Citrus Red No. 2 | GN68: Cladribine | GO68: Clarithromycin | GP68: Clobetasol propionate | GQ68: Clofibrate | GR68: Clomiphene citrate | GS68: Clorazepate dipotassium | GT68: CMNP (pyrazachlor) | GU68: Cobalt metal powder | GV68: Cobalt [II] oxide | GW68: Cobalt sulfate | GX68: Cobalt sulfate heptahydrate | GY68: Cocaine | GZ68: Coconut oil diethanolamine condensate (cocamide diethanolamine) | HA68: Codeine phosphate | HB68: Coke oven emissions | HC68: Colchicine | HD68: Conjugated estrogens | HE68: Creosotes | HF68: p-Cresidine | HG68: Cumene | HH68: Cupferron | HI68: Cyanazine | HJ68: Cycasin | HK68: Cycloate | HL68: Cycloheximide | HM68: Cyclopenta[cd]pyrene | HN68: Cyclophosphamide (anhydrous) | HO68: Cyclophosphamide (hydrated) | HP68: Cyhexatin | HQ68: Cytarabine | HR68: Cytembena | HS68: D&C Orange No. 17 | HT68: D&C Red No. 8 | HU68: D&C Red No. 9 | HV68: D&C Red No. 19 | HW68: Dacarbazine | HX68: Daminozide | HY68: Danazol | HZ68: Dantron (Chrysazin; 1,8-Dihydroxyanthraquinone) | IA68: Daunomycin | IB68: Daunorubicin hydrochloride | IC68: DDD (Dichlorodiphenyl-dichloroethane) | ID68: DDE (Dichlorodiphenyl-dichloroethylene) | IE68: DDT (Dichlorodiphenyl-trichloroethane) | IF68: o,p'-DDT | IG68: p,p'-DDT | IH68: DDVP (Dichlorvos) | II68: Demeclocycline hydrochloride (internal use) | IJ68: Des-ethyl atrazine (DEA) | IK68: Des-isopropyl atrazine (DIA) | IL68: N,N'-Diacetylbenzidine | IM68: 2,4-Diaminoanisole | IN68: 2,4-Diaminoanisole sulfate | IO68: 2,4-Diamino-6-chloro-s-triazine (DACT) | IP68: 4,4'-Diaminodiphenyl ether (4,4'-Oxydianiline) | IQ68: 2,4-Diaminotoluene | IR68: Diazepam | IS68: Diazoaminobenzene | IT68: Diazoxide | IU68: Dibenz[a,h]acridine | IV68: Dibenz[a,j]acridine | IW68: Dibenzanthracenes | IX68: Dibenz[a,c]anthracene | IY68: Dibenz[a,h]anthracene | IZ68: Dibenz[a,j]anthracene | JA68: 7H-Dibenzo[c,g]carbazole | JB68: Dibenzo[a,e]pyrene | JC68: Dibenzo[a,h]pyrene | JD68: Dibenzo[a,i]pyrene | JE68: Dibenzo[a,l]pyrene | JF68: Dibromoacetic acid | JG68: Dibromoacetonitrile | JH68: 1,2-Dibromo-3-chloropropane (DBCP) | JI68: 2,3-Dibromo-1-propanol | JJ68: Dichloroacetic acid | JK68: p-Dichlorobenzene | JL68: 3,3'-Dichlorobenzidine | JM68: 3,3'-Dichlorobenzidine dihydrochloride | JN68: 1,1-Dichloro-2,2-bis(p-chloropheny)ethylene (DDE) | JO68: 1,4-Dichloro-2-butene | JP68: 3,3'-Dichloro-4,4'-diamino-diphenyl ether | JQ68: 1,1-Dichloroethane | JR68: Dichloromethane (Methylene chloride) | JS68: 1,4-Dichloro-2-nitrobenzene | JT68: 2,4-Dichloro-1-nitrobenzene | JU68: Dichlorophene | JV68: Dichlorphenamide | JW68: 1,2-Dichloropropane | JX68: 1,3-Dichloro-2-propanol (1,3-DCP) | JY68: 1,3-Dichloropropene | JZ68: Diclofop-methyl | KA68: Diclofop methyl | KB68: Dicumarol | KC68: Dieldrin | KD68: Diepoxybutane | KE68: Diesel engine exhaust | KF68: Diethanolamine | KG68: Phthalates(Di(2-ethylhexyl)phthalate (DEHP),Di-n-hexyl phthalate (DnHP),Di-n-butyl phthalate (DBP),Diisononyl phthalate (DINP), Di-isodecyl phthalate (DIDP), Butyl benzyl phthalate (BBP)) | KH68: 1,2-Diethylhydrazine | KI68: Diethylstilbestrol (DES) | KJ68: Diethyl sulfate | KK68: Diflunisal | KL68: Diglycidyl resorcinol ether (DGRE) | KM68: Dihydroergotamine mesylate | KN68: Dihydrosafrole | KO68: Di-isodecyl phthalate (DIDP) | KP68: Diisononyl phthalate (DINP) | KQ68: Diisopropyl sulfate | KR68: Diltiazem hydrochloride | KS68: 3,3'-Dimethoxybenzidine (o-Dianisidine) | KT68: 3,3'-Dimethoxybenzidine dihydrochloride | KU68: 3,3'-Dimethoxybenzidine-based dyes metabolized to 3,3'-dimethoxybenzidine | KV68: N,N-Dimethylacetamide | KW68: 4-Dimethylaminoazobenzene | KX68: trans-2-[(Dimethylamino)methylimino]-5-[2-(5-nitro-2-furyl)vinyl]-1,3,4-oxadiazole | KY68: 7,12-Dimethylbenz(a)anthracene | KZ68: 3,3'-Dimethylbenzidine (ortho-Tolidine) | LA68: 3,3'-Dimethylbenzidine-based dyes metabolized to 3,3'-dimethylbenzidine | LB68: 3,3'-Dimethylbenzidine dihydrochloride | LC68: Dimethylcarbamoyl chloride | LD68: N,N-Dimethylformamide | LE68: 1,1-Dimethylhydrazine (UDMH) | LF68: 1,2-Dimethylhydrazine | LG68: Dimethyl hydrogen phosphite | LH68: 2,6-Dimethyl-N-nitrosomorpholine (DMNM) | LI68: Dimethyl sulfate | LJ68: N,N-Dimethyl-p-toluidine | LK68: Dimethylvinylchloride | LL68: Di-n-butyl phthalate (DBP) | LM68: Di-n-hexyl phthalate (DnHP) | LN68: m-Dinitrobenzene | LO68: o-Dinitrobenzene | LP68: p-Dinitrobenzene | LQ68: 3,7-Dinitrofluoranthene | LR68: 3,9-Dinitrofluoranthene | LS68: 1,3-Dinitropyrene | LT68: 1,6-Dinitropyrene | LU68: 1,8-Dinitropyrene | LV68: 2,4-Dinitrotoluene | LW68: 2,6-Dinitrotoluene | LX68: Dinitrotoluene (technical grade) | LY68: Dinitrotoluene mixture, 2,4-/2,6- | LZ68: Dinocap | MA68: Dinoseb | MB68: Di-n-propyl isocinchomeronate (MGK Repellent 326) | MC68: 1,4-Dioxane | MD68: Diphenylhydantoin (Phenytoin) | ME68: Diphenylhydantoin (Phenytoin), sodium salt | MF68: Direct Black 38 (technical grade) | MG68: Direct Blue 6 (technical grade) | MH68: Direct Brown 95 (technical grade) | MI68: Disodium cyanodithioimidocarbonate | MJ68: Disperse Blue 1 | MK68: Diuron | ML68: Doxorubicin hydrochloride (Adriamycin) | MM68: Doxycycline (internal use) | MN68: Doxycycline calcium (internal use) | MO68: Doxycycline hyclate (internal use) | MP68: Doxycycline monohydrate (internal use) | MQ68: Emissions from combustion of coal | MR68: Emissions from high-temperature unrefined rapeseed oil | MS68: Endrin | MT68: Environmental tobacco smoke (ETS) | MU68: Epichlorohydrin | MV68: Epoxiconazole | MW68: Ergotamine tartrate | MX68: Erionite | MY68: Estradiol 17B | MZ68: Estragole | NA68: Estrogens, steroidal | NB68: Estrogen-progestogen (combined) used as menopausal therapy | NC68: Estrone | ND68: Estropipate | NE68: Ethinylestradiol | NF68: Ethionamide | NG68: Ethoprop | NH68: Ethyl acrylate | NI68: Ethyl alcohol in alcoholic beverages | NJ68: Ethylbenzene | NK68: Ethyl dipropylthiocarbamate | NL68: Ethyl-4,4'-dichlorobenzilate | NM68: Ethylene dibromide | NN68: Ethylene dichloride (1,2-Dichloroethane) | NO68: Ethylene glycol (ingested) | NP68: Ethylene glycol monoethyl ether | NQ68: Ethylene glycol monoethyl ether acetate | NR68: Ethylene glycol monomethyl ether | NS68: Ethylene glycol monomethyl ether acetate | NT68: Ethyleneimine (Aziridine) | NU68: Ethylene oxide | NV68: Ethylene thiourea | NW68: 2-Ethylhexyl acrylate | NX68: Ethyl methanesulfonate | NY68: Etodolac | NZ68: Etoposide | OA68: Etoposide in combination with cisplatin and bleomycin | OB68: Etretinate | OC68: Fenoxaprop ethyl | OD68: Fenoxycarb | OE68: Filgrastim | OF68: Fluazifop butyl | OG68: Flunisolide | OH68: Fluorouracil | OI68: Fluoxymesterone | OJ68: Flurazepam hydrochloride | OK68: Flurbiprofen | OL68: Flutamide | OM68: Fluticasone propionate | ON68: Fluvalinate | OO68: Folpet | OP68: Formaldehyde(gas) | OQ68: 2-(2-Formylhydrazino)-4-(5-nitro-2-furyl)thiazole | OR68: Fumonisin B1 | OS68: Furan | OT68: Furazolidone | OU68: Furfuryl alcohol | OV68: Furmecyclox | OW68: Fusarin C | OX68: Gallium arsenide | OY68: Ganciclovir | OZ68: Ganciclovir sodium | PA68: Gasoline engine exhaust (condensates/extracts) | PB68: Gemfibrozil | PC68: Gentian violet (Crystal violet) | PD68: Glass wool fibers (inhalable and biopersistent) | PE68: Glu-P-1 (2-Amino-6-methyldipyrido[1,2- a:3',2'-d]imidazole) | PF68: Glu-P-2 (2-Aminodipyrido[1,2-a:3',2'-d]imidazole) | PG68: Glycidaldehyde | PH68: Glycidol | PI68: Glycidyl methacrylate | PJ68: Glyphosate | PK68: Goldenseal root powder | PL68: Goserelin acetate | PM68: Griseofulvin | PN68: Gyromitrin (Acetaldehyde methylformylhydrazone) | PO68: Halazepam | PP68: Halobetasol propionate | PQ68: Haloperidol | PR68: Halothane | PS68: HC Blue 1 | PT68: Heptachlor | PU68: Heptachlor epoxide | PV68: Herbal remedies containing plant species of the genus Aristolochia | PW68: Hexachlorobenzene | PX68: Hexachlorobutadiene | PY68: Hexachlorocyclohexane (technical grade) | PZ68: Hexachlorocyclohexane (alpha isomer) | QA68: Hexachlorocyclohexane (beta isomer) | QB68: Hexachlorocyclohexane (gamma isomer) | QC68: Hexachlorodibenzodioxin | QD68: Hexachloroethane | QE68: 2,4-Hexadienal (89% trans, trans isomer; 11% cis, trans isomer) | QF68: Hexafluoroacetone | QG68: Hexamethylphosphoramide | QH68: n-Hexane | QI68: 2,5-Hexanedione | QJ68: Histrelin acetate | QK68: Hydramethylnon | QL68: Hydrazine | QM68: Hydrazine sulfate | QN68: Hydrazobenzene (1,2-Diphenylhydrazine) | QO68: Hydrogen cyanide (HCN) and cyanide salts (CN salts) | QP68: Cyanide salts that readily dissociate in solution (expressed as cyanide) | QQ68: Hydrogen cyanide | QR68: Sodium cyanide | QS68: Potassium cyanide | QT68: 1-Hydroxyanthraquinone | QU68: Hydroxyurea | QV68: Idarubicin hydrochloride | QW68: Ifosfamide | QX68: Iodine-131 | QY68: Imazalil | QZ68: Indeno[1,2,3-cd]pyrene | RA68: Indium phosphide | RB68: Indium tin oxide | RC68: IQ (2-Amino-3-methylimidazo[4,5-f] quinoline) | RD68: Iprodione | RE68: Iprovalicarb | RF68: Iron dextran complex | RG68: Isobutyl nitrite | RH68: Isoprene | RI68: Isopyrazam | RJ68: Isotretinoin | RK68: Isoxaflutole | RL68: Kresoxim-methyl | RM68: Lactofen | RN68: Lasiocarpine | RO68: Lead | RP68: Lead and lead compounds | RQ68: Lead acetate | RR68: Lead phosphate | RS68: Lead subacetate | RT68: Leather dust | RU68: Leucomalachite green | RV68: Leuprolide acetate | RW68: Levodopa | RX68: Levonorgestrel implants | RY68: Lindane and other hexachlorocyclohexane isomers | RZ68: Linuron | SA68: Lithium carbonate | SB68: Lithium citrate | SC68: Lorazepam | SD68: Lovastatin | SE68: Lynestrenol | SF68: Malathion | SG68: Malonaldehyde, sodium salt | SH68: Mancozeb | SI68: Maneb | SJ68: Marijuana smoke | SK68: Me-A-alpha-C (2-Amino-3-methyl-9H-pyrido[2,3-b]indole) | SL68: Mebendazole | SM68: Medroxyprogesterone acetate | SN68: Megestrol acetate | SO68: MeIQ (2-Amino-3,4-dimethylimidazo[4,5-f]quinoline) | SP68: MeIQx (2-Amino-3,8-dimethylimidazo[4,5-f]quinoxaline) | SQ68: Melphalan | SR68: Menotropins | SS68: Mepanipyrim | ST68: Meprobamate | SU68: 2‑Mercaptobenzothiazole | SV68: Mercaptopurine | SW68: Mercury and mercury compounds | SX68: Merphalan | SY68: Mestranol | SZ68: Metam potassium | TA68: Methacycline hydrochloride | TB68: Metham sodium | TC68: Methanol | TD68: Methazole | TE68: Methimazole | TF68: Methotrexate | TG68: Methotrexate sodium | TH68: 5-Methoxypsoralen with ultraviolet A therapy | TI68: 8-Methoxypsoralen with ultraviolet A therapy | TJ68: Methyl acrylate | TK68: 2-Methylaziridine (Propyleneimine) | TL68: Methylazoxymethanol | TM68: Methylazoxymethanol acetate | TN68: Methyl bromide, as a structural fumigant | TO68: Methyl carbamate | TP68: Methyl chloride | TQ68: 3-Methylcholanthrene | TR68: 5-Methylchrysene | TS68: 4,4'-Methylene bis(2-chloroaniline) | TT68: 4,4'-Methylene bis(N,N-dimethyl)benzenamine | TU68: 4,4'-Methylene bis(2-methylaniline) | TV68: 4,4'-Methylenedianiline | TW68: 4,4'-Methylenedianiline dihydrochloride | TX68: Methyleugenol | TY68: Methylhydrazine and its salts | TZ68: Methylhydrazine | UA68: Methylhydrazine sulfate | UB68: 2-Methylimidazole | UC68: 4-Methylimidazole | UD68: Methyl iodide | UE68: Methyl isobutyl ketone | UF68: Methyl isocyanate | UG68: Methyl mercury | UH68: Methylmercury compounds | UI68: Methyl methanesulfonate | UJ68: Methyl-n-butyl ketone | UK68: 2-Methyl-1-nitroanthraquinone (of uncertain purity) | UL68: N-Methyl-N'-nitro-N-nitrosoguanidine | UM68: N-Methylolacrylamide | UN68: N-Methylpyrrolidone | UO68: α-Methyl styrene (alpha-Methylstyrene) | UP68: Methyltestosterone | UQ68: Methylthiouracil | UR68: Metiram | US68: Metronidazole | UT68: Michler's ketone | UU68: Midazolam hydrochloride | UV68: Minocycline hydrochloride (internal use) | UW68: Mirex | UX68: Misoprostol | UY68: Mitomycin C | UZ68: Mitoxantrone hydrochloride | VA68: Molinate | VB68: Molybdenum trioxide | VC68: MON 4660 (dichloroacetyl-1-oxa-4-azaspiro(4,5)-decane） | VD68: MON 13900 (furilazole) | VE68: 3-Monochloropropane-1,2-diol (3-MCPD) | VF68: Monocrotaline | VG68: MOPP (vincristine-prednisone-nitrogen mustard-procarbazine mixture) | VH68: 5-(Morpholinomethyl)-3-[(5-nitrofurfuryl-idene)-amino]-2-oxazolidinone | VI68: Mustard Gas | VJ68: MX (3-chloro-4-dichloromethyl-5-hydroxy-2(5H)-furanone) | VK68: Myclobutanil | VL68: beta-Myrcene | VM68: Nabam | VN68: Nafarelin acetate | VO68: Nafenopin | VP68: Nalidixic acid | VQ68: Naphthalene | VR68: 1-Naphthylamine | VS68: 2-Naphthylamine | VT68: Neomycin sulfate (internal use) | VU68: Netilmicin sulfate | VV68: Nickel (Metallic) | VW68: Nickel acetate | VX68: Nickel carbonate | VY68: Nickel carbonyl | VZ68: Nickel compounds | WA68: Nickel (soluble compounds) | WB68: Nickel hydroxide | WC68: Nickelocene | WD68: Nickel oxide | WE68: Nickel refinery dust from the pyrometallurgical process | WF68: Nickel subsulfide | WG68: Nicotine | WH68: Nifedipine | WI68: Nimodipine | WJ68: Niridazole | WK68: Nitrapyrin | WL68: Nitrilotriacetic acid | WM68: Nitrilotriacetic acid, trisodium salt monohydrate | WN68: 5-Nitroacenaphthene | WO68: o-Nitroanisole | WP68: para-Nitroanisole | WQ68: Nitrobenzene | WR68: 4-Nitrobiphenyl | WS68: 6-Nitrochrysene | WT68: Nitrofen (technical grade) | WU68: 2-Nitrofluorene | WV68: Nitrofurantoin | WW68: Nitrofurazone | WX68: 1-[(5-Nitrofurfurylidene)-amino]-2-imidazolidinone | WY68: N-[4-(5-Nitro-2-furyl)-2-thiazolyl]acetamide | WZ68: Nitrogen mustard (Mechlorethamine) | XA68: Nitrogen mustard hydrochloride (Mechlorethamine hydrochloride) | XB68: Nitrogen mustard N-oxide | XC68: Nitrogen mustard N-oxide hydrochloride | XD68: Nitromethane | XE68: 2-Nitropropane | XF68: 1-Nitropyrene | XG68: 4-Nitropyrene | XH68: N-Nitrosodi-n-butylamine | XI68: N-Nitrosodiethanolamine | XJ68: N-Nitrosodiethylamine | XK68: N-Nitrosodimethylamine | XL68: p-Nitrosodiphenylamine | XM68: N-Nitrosodiphenylamine | XN68: N-Nitrosodi-n-propylamine | XO68: N-Nitroso-N-ethylurea | XP68: N-Nitrosohexamethyleneimine | XQ68: 3-(N-Nitrosomethylamino) propionitrile | XR68: 4-(N-Nitrosomethylamino)-1-(3-pyridyl)1-butanone | XS68: N-Nitrosomethyl-n-butylamine | XT68: N-Nitrosomethyl-n-decylamine | XU68: N-Nitrosomethyl-n-dodecylamine | XV68: N-Nitrosomethylethylamine | XW68: N-Nitrosomethyl-n-heptylamine | XX68: N-Nitrosomethyl-n-hexylamine | XY68: N-Nitrosomethyl-n-nonylamine | XZ68: N-Nitrosomethyl-n-octylamine | YA68: N-Nitrosomethyl-n-pentylamine | YB68: N-Nitrosomethyl-n-propylamine | YC68: N-Nitrosomethyl-n-tetradecylamine | YD68: N-Nitrosomethyl-n-undecylamine | YE68: N-Nitroso-N-methylurea | YF68: N-Nitroso-N-methylurethane | YG68: N-Nitrosomethylvinylamine | YH68: N-Nitrosomorpholine | YI68: N-Nitrosonornicotine | YJ68: N-Nitrosopiperidine | YK68: N-Nitrosopyrrolidine | YL68: N-Nitrososarcosine | YM68: o-Nitrotoluene | YN68: Nitrous oxide | YO68: Norethisterone (Norethindrone) | YP68: Norethisterone acetate (Norethindrone acetate) | YQ68: Norethisterone (Norethindrone) /Ethinyl estradiol | YR68: Norethisterone (Norethindrone) /Mestranol | YS68: Norethynodrel | YT68: Norgestrel | YU68: Ochratoxin A | YV68: Oil Orange SS | YW68: Oral contraceptives, combined | YX68: Oral contraceptives, sequential | YY68: Oryzalin | YZ68: Oxadiazon | ZA68: Oxazepam | ZB68: Oxydemeton methyl | ZC68: Oxymetholone | ZD68: Oxytetracycline (internal use) | ZE68: Oxytetracycline hydrochloride (internal use) | ZF68: Oxythioquinox (Chinomethionat) | ZG68: Paclitaxel | ZH68: Palygorskite fibers (> 5µm in length) | ZI68: Panfuran S | ZJ68: Paramethadione | ZK68: Parathion | ZL68: Penicillamine | ZM68: pentabromodiphenyl ether mixture [DE-71 (technical grade)] | ZN68: Pentachlorophenol | ZO68: Pentachlorophenol and by-products of its synthesis (complex mixture) | ZP68: Pentobarbital sodium | ZQ68: Pentosan polysulfate sodium | ZR68: Pentostatin | ZS68: Perfluorononanoic acid (PFNA) and its salts | ZT68: Perfluorooctane sulfonate (PFOS) | ZU68: Perfluorooctane sulfonic acid (PFOS) and its salts and transformation and degradation precursors | ZV68: Perfluorooctanoic acid (PFOA) | ZW68: Pertuzumab | ZX68: Phenacemide | ZY68: Phenacetin | ZZ68: Phenazopyridine | AAA68: Phenazopyridine hydrochloride | AAB68: Phenesterin | AAC68: Phenobarbital | AAD68: Phenolphthalein | AAE68: Phenoxybenzamine | AAF68: Phenoxybenzamine hydrochloride | AAG68: Phenprocoumon | AAH68: o-Phenylenediamine and its salts | AAI68: o-Phenylenediamine | AAJ68: o-Phenylenediamine dihydrochloride | AAK68: Phenyl glycidyl ether | AAL68: Phenylhydrazine and its salts | AAM68: Phenylhydrazine | AAN68: Phenylhydrazine hydrochloride | AAO68: o-Phenylphenate, sodium | AAP68: o-Phenylphenol | AAQ68: Phenylphosphine | AAR68: PhiP(2-Amino-1-methyl-6-phenylimidazol[4,5-b]pyridine) | AAS68: Pimozide | AAT68: Pioglitazone | AAU68: Pipobroman | AAV68: Pirimicarb | AAW68: Plicamycin | AAX68: Polybrominated biphenyls | AAY68: Polychlorinated biphenyls | AAZ68: Polychlorinated biphenyls (containing 60 or more percent chlorine by molecular weight) | ABA68: Polychlorinated dibenzo-p-dioxins | ABB68: Polychlorinated dibenzofurans | ABC68: Polygeenan | ABD68: Ponceau MX | ABE68: Ponceau 3R | ABF68: Potassium bromate | ABG68: Potassium dimethyldithiocarbamate | ABH68: Pravastatin sodium | ABI68: Prednisolone sodium phosphate | ABJ68: Primidone | ABK68: Procarbazine | ABL68: Procarbazine hydrochloride | ABM68: Procymidone | ABN68: Progesterone | ABO68: Pronamide | ABP68: Propachlor | ABQ68: 1,3-Propane sultone | ABR68: Propargite | ABS68: Propazine | ABT68: beta-Propiolactone | ABU68: Propoxur | ABV68: Propylene glycol mono-t-butyl ether | ABW68: Propylene oxide | ABX68: Propylthiouracil | ABY68: Pulegone | ABZ68: Pymetrozine | ACA68: Pyridine | ACB68: Pyrimethamine | ACC68: Quazepam | ACD68: Quinoline and its strong acid salts | ACE68: Quizalofop-ethyl | ACF68: Radionuclides | ACG68: Reserpine | ACH68: Residual (heavy) fuel oils | ACI68: Resmethrin | ACJ68: Retinol(retinyl esters) | ACK68: Ribavirin | ACL68: Riddelliine | ACM68: Rifampin | ACN68: Safrole | ACO68: Salted fish, Chinese-style | ACP68: Secobarbital sodium | ACQ68: Sedaxane | ACR68: Selenium sulfide | ACS68: Sermorelin acetate | ACT68: Shale-oils | ACU68: Silica, crystalline (airborne particles of respirable size) | ACV68: Simazine | ACW68: Sodium dimethyldithiocarbamate | ACX68: Sodium fluoroacetate | ACY68: Soots, tars, and mineral oils (untreated and mildly treated oils and used engine oils) | ACZ68: Spirodiclofen | ADA68: Spironolactone | ADB68: Stanozolol | ADC68: Sterigmatocystin | ADD68: Streptomycin sulfate | ADE68: Streptozocin (streptozotocin) | ADF68: Streptozotocin (streptozocin) | ADG68: Strong inorganic acid mists containing sulfuric acid | ADH68: Styrene | ADI68: Styrene oxide | ADJ68: Sulfallate | ADK68: Sulfasalazine (Salicylazosulfapyridine) | ADL68: Sulfur dioxidee | ADM68: Sulindac | ADN68: Talc containing asbestiform fibers | ADO68: Tamoxifen and its salts | ADP68: Tamoxifen citrate | ADQ68: Temazepam | ADR68: Teniposide | ADS68: Terbacil | ADT68: Teriparatide | ADU68: Terrazole | ADV68: Testosterone and its esters | ADW68: Testosterone cypionate | ADX68: Testosterone enanthate | ADY68: Tetrabromobisphenol A | ADZ68: 3,3',4,4'-Tetrachloroazobenzene | AEA68: 2,3,7,8-Tetrachlorodibenzo-p-dioxin (TCDD) | AEB68: 1,1,1,2-Tetrachloroethane | AEC68: 1,1,2,2-Tetrachloroethane | AED68: Tetrachloroethylene (Perchloroethylene) | AEE68: p-a,a,a-Tetrachlorotoluene | AEF68: Tetrachlorvinphos | AEG68: Tetracycline (internal use) | AEH68: Tetracyclines (internal use) | AEI68: Tetracycline hydrochloride (internal use) | AEJ68: Tetrafluoroethylene | AEK68: Δ9-Tetrahydrocannabinol (Δ9-THC) | AEL68: Tetrahydrofuran | AEM68: Tetranitromethane | AEN68: Thalidomide | AEO68: Thioacetamide | AEP68: 4,4'-Thiodianiline | AEQ68: Thiodicarb | AER68: Thioguanine | AES68: Thiophanate methyl | AET68: Thiouracil | AEU68: Thiourea | AEV68: Thorium dioxide | AEW68: Titanium dioxide (airborne, unbound particles of respirable size) | AEX68: Tobacco, oral use of smokeless products | AEY68: Tobacco smoke | AEZ68: Tobacco smoke (primary) | AFA68: Tobramycin sulfate | AFB68: Toluene | AFC68: Toluene diisocyanate | AFD68: o-Toluidine | AFE68: o-Toluidine hydrochloride | AFF68: Topiramate | AFG68: Toxaphene (Polychlorinated camphenes) | AFH68: Toxins derived from Fusarium moniliforme (Fusarium verticillioides) | AFI68: Treosulfan | AFJ68: Triadimefon | AFK68: Triamterene | AFL68: Triazolam | AFM68: S,S,S-Tributyl phosphorotrithioate (Tribufos, DEF) | AFN68: Tributyltin methacrylate | AFO68: Trichlormethine (Trimustine hydrochloride) | AFP68: Trichloroacetic acid | AFQ68: 1,1,1-Trichloroethane | AFR68: Trichloroethylene | AFS68: 2,4,6-Trichlorophenol | AFT68: 1,2,3-Trichloropropane | AFU68: Trientine hydrochloride | AFV68: Triforine | AFW68: Trilostane | AFX68: Trimethadione | AFY68: 2,4,5-Trimethylaniline and its strong acid salts | AFZ68: Trimethylolpropane triacrylate, technical grade | AGA68: Trimethyl phosphate | AGB68: Trimetrexate glucuronate | AGC68: TRIM® VX | AGD68: 2,4,6-Trinitrotoluene (TNT) | AGE68: Triphenyltin hydroxide | AGF68: Tris(1-aziridinyl)phosphine sulfide (Thiotepa) | AGG68: Tris(2-chloroethyl) phosphate | AGH68: Tris(2,3-dibromopropyl)phosphate | AGI68: Tris(1,3-dichloro-2-propyl) phosphate (TDCPP) | AGJ68: Trp-P-1 (Tryptophan-P-1) | AGK68: Trp-P-2 (Tryptophan-P-2) | AGL68: Trypan blue (commercial grade) | AGM68: Unleaded gasoline (wholly vaporized) | AGN68: Uracil mustard | AGO68: Urethane (Ethyl carbamate) | AGP68: Urofollitropin | AGQ68: Valproate (Valproic acid) | AGR68: Vanadium pentoxide (orthorhombic crystalline form) | AGS68: Vinblastine sulfate | AGT68: Vinclozolin | AGU68: Vincristine sulfate | AGV68: Vinyl bromide | AGW68: Vinyl chloride | AGX68: 4-Vinylcyclohexene | AGY68: 4-Vinyl-1-cyclohexene diepoxide (Vinyl cyclohexene dioxide) | AGZ68: Vinyl fluoride | AHA68: Vinylidene chloride (1,1-Dichloroethylene) | AHB68: Vinyl trichloride (1,1,2-Trichloroethane) | AHC68: Vismodegib | AHD68: Warfarin | AHE68: Wood dust | AHF68: 2,6-Xylidine (2,6-Dimethylaniline) | AHG68: Zalcitabine | AHH68: Zidovudine (AZT) | AHI68: Zileuton | AHJ68: Arsenic | AHK68: Nickel and nickel compounds | AHL68: Di(2-ethylhexyl)phthalate (DEHP) | AHM68: Phosphate triester | AHN68: Antimony trioxide,Chlorinated tris [tris(1,3-dichloro-2-propyl)phosphate, TDCPP, and TDCIPP],Pentabromodiphenyl ether (PentaBDE),Tetrabromobisphenol A (TBBPA),Tris(2-chloroethyl) phosphate (TCEP) | AHO68: Formaldehyde (gas) | AHP68: Bisphenol S (BPS)

Sheet GoodsLevelMode
A1: t_0_Goods Id | B1: t_0_Sku Id | C1: t_0_Status | D1: t_0_Details | E1: t_1_Category | F1: t_1_Category Name | G1: t_1_Product type | H1: t_1_Customization processing technique | I1: t_1_Primary technique | J1: t_1_Secondary technique | K1: t_1_Secondary technique | L1: t_1_Product Name | M1: t_1_Contribution Goods | N1: t_1_Contribution SKU | O1: t_1_Update or Add | P1: t_1_Goods Id | Q1: t_1_Sku Id | R1: t_1_Brand | S1: t_1_Trademark | T1: t_2_Product Description | U1: t_2_Bullet Point | V1: t_2_Bullet Point | W1: t_2_Bullet Point | X1: t_2_Bullet Point | Y1: t_2_Bullet Point | Z1: t_2_Bullet Point | AA1: t_2_Detail Images URL | AB1: t_2_Detail Images URL | AC1: t_2_Detail Images URL | AD1: t_2_Detail Images URL | AE1: t_2_Detail Images URL | AF1: t_2_Detail Images URL | AG1: t_2_Detail Images URL | AH1: t_2_Detail Images URL | AI1: t_2_Detail Images URL | AJ1: t_2_Detail Images URL | AK1: t_2_Detail Images URL | AL1: t_2_Detail Images URL | AM1: t_2_Detail Images URL | AN1: t_2_Detail Images URL | AO1: t_2_Detail Images URL | AP1: t_2_Detail Images URL | AQ1: t_2_Detail Images URL | AR1: t_2_Detail Images URL | AS1: t_2_Detail Images URL | AT1: t_2_Detail Images URL | AU1: t_2_Detail Images URL | AV1: t_2_Detail Images URL | AW1: t_2_Detail Images URL | AX1: t_2_Detail Images URL | AY1: t_2_Detail Images URL | AZ1: t_2_Detail Images URL | BA1: t_2_Detail Images URL | BB1: t_2_Detail Images URL | BC1: t_2_Detail Images URL | BD1: t_2_Detail Images URL | BE1: t_2_Detail Images URL | BF1: t_2_Detail Images URL | BG1: t_2_Detail Images URL | BH1: t_2_Detail Images URL | BI1: t_2_Detail Images URL | BJ1: t_2_Detail Images URL | BK1: t_2_Detail Images URL | BL1: t_2_Detail Images URL | BM1: t_2_Detail Images URL | BN1: t_2_Detail Images URL | BO1: t_2_Detail Images URL | BP1: t_2_Detail Images URL | BQ1: t_2_Detail Images URL | BR1: t_2_Detail Images URL | BS1: t_2_Detail Images URL | BT1: t_2_Detail Images URL | BU1: t_2_Detail Images URL | BV1: t_2_Detail Images URL | BW1: t_2_Detail Images URL | BX1: t_2_Detail Images URL | BY1: t_2_Detail Images URL | BZ1: t_2_Detail Images URL | CA1: t_2_Detail Images URL | CB1: t_2_Detail Images URL | CC1: t_2_Detail Images URL | CD1: t_2_Detail Images URL | CE1: t_2_Detail Images URL | CF1: t_2_Detail Images URL | CG1: t_2_Detail Images URL | CH1: t_2_Detail Images URL | CI1: t_2_Detail Images URL | CJ1: t_2_Detail Images URL | CK1: t_2_Detail Images URL | CL1: t_2_Detail Images URL | CM1: t_2_Detail Images URL | CN1: t_2_Detail Images URL | CO1: t_2_Detail Images URL | CP1: t_2_Detail Images URL | CQ1: t_2_Detail Images URL | CR1: t_2_Detail Images URL | CS1: t_2_Detail Images URL | CT1: t_2_Detail Images URL | CU1: t_2_Detail Images URL | CV1: t_2_Detail Images URL | CW1: t_2_Detail Images URL | CX1: t_2_Detail Images URL | CY1: t_2_Detail Images URL | CZ1: t_2_Detail Images URL | DA1: t_2_Detail Images URL | DB1: t_2_Detail Images URL | DC1: t_2_Detail Images URL | DD1: t_2_Detail Images URL | DE1: t_2_Detail Images URL | DF1: t_2_Detail Images URL | DG1: t_2_Detail Images URL | DH1: t_2_Detail Images URL | DI1: t_2_Detail Images URL | DJ1: t_2_Detail Images URL | DK1: t_2_Detail Images URL | DL1: t_2_Detail Images URL | DM1: t_2_Detail Images URL | DN1: t_2_Detail Images URL | DO1: t_2_Detail Images URL | DP1: t_2_Detail Images URL | DQ1: t_2_Detail Images URL | DR1: t_2_Detail Video URL | DS1: t_3_Property:19 | DT1: t_3_Property:423 | DU1: t_3_Property:423 | DV1: t_3_Property:423 | DW1: t_3_Property:423 | DX1: t_3_Property:423 | DY1: t_3_Property:127 | DZ1: t_3_Property:121 | EA1: t_3_Property:130 | EB1: t_3_Property:2232 | EC1: t_3_Property:2233|2232 | ED1: t_3_Property:1561 | EE1: t_3_Property:1132|1561 | EF1: t_3_Property:1562|1561 | EG1: t_3_Property:137|1561 | EH1: t_3_Property:1563|1561 | EI1: t_3_Property:1485|1561 | EJ1: t_3_Property:2147|1561 | EK1: t_3_Property:2154|1561 | EL1: t_3_Property:111|1561 | EM1: t_3_Property:2028 - value|1561 | EN1: t_3_Property:2028 - unit|1561 | EO1: t_3_Property:3673 | EP1: t_3_Property:7644 | EQ1: t_4_Variation Theme | ER1: t_4_Custom Spec:1001 | ES1: t_4_Custom Spec:3001 | ET1: t_4_Custom Spec:18012 | EU1: t_4_Custom Spec:17017 | EV1: t_4_Custom Spec:18013 | EW1: t_4_Custom Spec:17018 | EX1: t_4_Custom Spec:18014 | EY1: t_4_Custom Spec:17019 | EZ1: t_4_Custom Spec:18016 | FA1: t_4_Custom Spec:17020 | FB1: t_4_Custom Spec:15998553 | FC1: t_4_Custom Spec:45114199 | FD1: t_4_Custom Spec:44214483 | FE1: t_6_SKU Images URL | FF1: t_6_SKU Images URL | FG1: t_6_SKU Images URL | FH1: t_6_SKU Images URL | FI1: t_6_SKU Images URL | FJ1: t_6_SKU Images URL | FK1: t_6_SKU Images URL | FL1: t_6_SKU Images URL | FM1: t_6_SKU Images URL | FN1: t_6_SKU Images URL | FO1: t_6_Dimensions | FP1: t_6_Quantity | FQ1: t_6_Base Price - USD | FR1: t_6_Reference Link | FS1: t_6_List Price - USD | FT1: t_6_Weight - lb | FU1: t_6_Length - in | FV1: t_6_Width - in | FW1: t_6_Height - in | FX1: t_6_SKU type | FY1: t_6_Individually packed | FZ1: t_6_Total packaging quantity | GA1: t_6_Packaging unit | GB1: t_6_Total item quantity | GC1: t_6_Item unit | GD1: t_6_Net content | GE1: t_6_Total net content | GF1: t_6_Net content unit | GG1: t_6_External Product ID Type | GH1: t_6_External Product ID | GI1: t_7_Shipping Template | GJ1: t_7_Handling Time | GK1: t_7_Import Designation | GL1: t_7_Fulfillment Channel | GM1: t_8_Country/Region of Origin | GN1: t_8_Province of Origin | GO1: t_8_SKU Packaging Information (with visible label) | GP1: t_8_SKU Packaging Information (with visible label) | GQ1: t_8_SKU Packaging Information (with visible label) | GR1: t_8_SKU Packaging Information (with visible label) | GS1: t_8_SKU Packaging Information (with visible label) | GT1: t_8_SKU Packaging Information (with visible label) | GU1: t_8_SKU Packaging Information (with visible label) | GV1: t_8_SKU Packaging Information (with visible label) | GW1: t_8_SKU Packaging Information (with visible label) | GX1: t_8_SKU Packaging Information (with visible label) | GY1: t_8_SKU Packaging Information (with visible label) | GZ1: t_8_SKU Packaging Information (with visible label) | HA1: t_8_SKU Packaging Information (with visible label) | HB1: t_8_SKU Packaging Information (with visible label) | HC1: t_8_SKU Packaging Information (with visible label) | HD1: t_8_SKU Packaging Information (with visible label) | HE1: t_8_SKU Packaging Information (with visible label) | HF1: t_8_SKU Packaging Information (with visible label) | HG1: t_8_SKU Packaging Information (with visible label) | HH1: t_8_SKU Packaging Information (with visible label) | HI1: t_8_SKU Packaging Information (with visible label) | HJ1: t_8_SKU Packaging Information (with visible label) | HK1: t_8_SKU Packaging Information (with visible label) | HL1: t_8_SKU Packaging Information (with visible label) | HM1: t_8_SKU Packaging Information (with visible label) | HN1: t_8_SKU Packaging Information (with visible label) | HO1: t_8_SKU Packaging Information (with visible label) | HP1: t_8_SKU Packaging Information (with visible label) | HQ1: t_8_SKU Packaging Information (with visible label) | HR1: t_8_SKU Packaging Information (with visible label) | HS1: t_8_SKU Packaging Information (with visible label) | HT1: t_8_SKU Packaging Information (with visible label) | HU1: t_8_SKU Packaging Information (with visible label) | HV1: t_8_SKU Packaging Information (with visible label) | HW1: t_8_SKU Packaging Information (with visible label) | HX1: t_8_SKU Packaging Information (with visible label) | HY1: t_8_SKU Packaging Information (with visible label) | HZ1: t_8_SKU Packaging Information (with visible label) | IA1: t_8_SKU Packaging Information (with visible label) | IB1: t_8_SKU Packaging Information (with visible label) | IC1: t_8_SKU Packaging Information (with visible label) | ID1: t_8_SKU Packaging Information (with visible label) | IE1: t_8_SKU Packaging Information (with visible label) | IF1: t_8_SKU Packaging Information (with visible label) | IG1: t_8_SKU Packaging Information (with visible label) | IH1: t_8_Origin Label & Manufacturer Information | II1: t_8_Origin Label & Manufacturer Information | IJ1: t_8_Origin Label & Manufacturer Information | IK1: t_8_Origin Label & Manufacturer Information | IL1: t_8_Origin Label & Manufacturer Information | IM1: t_8_Product Guide | IN1: t_8_Governance Property:1000000001 | IO1: t_8_Governance Property:1000000002
A2: 12155_require | E2: require | L2: require | M2: require | N2: require | ED2: require | EQ2: require | FE2: require | FP2: require | FQ2: require | FT2: require | FU2: require | FV2: require | FW2: require | FY2: require | FZ2: require | GA2: require | GI2: require | GM2: require
A3: 12155_disabled
A4: 12155_condition_require | EE4: condition_require | EI4: condition_require | GN4: condition_require

Sheet Browse Data
A1: 12155 | B1: Home & Kitchen / Home Décor Products / Home Décor Accents / Wreaths

Sheet Valid Values
A1: Product Identity
B2: Category | C2: 12155
B3: Product type | C3: Normal product | D3: Custom product
B4: Customization processing technique - [Custom product] | C4: Single technique | D4: Combined techniques
B5: Primary technique - [Combined techniques] - [Custom product] | C5: Canvas/paper customization technique | D5: Organic material (e.g., acrylic/resin) customization technique | E5: Wood product customization technique | F5: Metal product customization technique | G5: Leather/fabric customization technique
B6: Primary technique - [Single technique] - [Custom product] | C6: Basic technique | D6: Canvas/paper customization technique | E6: Organic material (e.g., acrylic/resin) customization technique | F6: Wood product customization technique | G6: Metal product customization technique | H6: Leather/fabric customization technique
B7: Secondary technique - [Canvas/paper customization technique] - [Combined techniques] - [Custom product] | C7: Silk screen printing - text | D7: Silk screen printing - image | E7: Hot stamping - text | F7: Hot stamping - image | G7: Debossing
B8: Secondary technique - [Leather/fabric customization technique] - [Combined techniques] - [Custom product] | C8: Laser engraving - text | D8: Laser engraving - images | E8: UV | F8: Silk screen printing - text | G8: Silk screen printing - image | H8: Soft enamel | I8: Hot stamping - text | J8: Hot stamping - image | K8: Debossing
B9: Secondary technique - [Metal product customization technique] - [Combined techniques] - [Custom product] | C9: Laser engraving - text | D9: Laser engraving - images | E9: Mechanical engraving - text | F9: Debossing | G9: Welding | H9: UV | I9: Silk screen printing - text | J9: Silk screen printing - image | K9: Spray painting | L9: Soft enamel | M9: Laser cutting - text | N9: Laser cutting - image | O9: Rhinestone setting | P9: Electroplating
B10: Secondary technique - [Organic material (e.g., acrylic/resin) customization technique] - [Combined techniques] - [Custom product] | C10: Laser engraving - text | D10: Laser engraving - images | E10: Mechanical engraving - text | F10: Debossing | G10: UV | H10: Silk screen printing - text | I10: Silk screen printing - image | J10: Laser cutting - text | K10: Laser cutting - image
B11: Secondary technique - [Wood product customization technique] - [Combined techniques] - [Custom product] | C11: Laser engraving - text | D11: Laser engraving - images | E11: Mechanical engraving - text | F11: Debossing
B12: Secondary technique - [Canvas/paper customization technique] - [Single technique] - [Custom product] | C12: Hand-painting - sketch | D12: Hand-painting - watercolor | E12: Hand-painting - oil painting | F12: Hand-painting - printmaking | G12: Hand-painting - comic | H12: Debossing
B13: Secondary technique - [Leather/fabric customization technique] - [Single technique] - [Custom product] | C13: Laser engraving - text | D13: Laser engraving - images | E13: UV | F13: Silk screen printing - text | G13: Silk screen printing - image | H13: Soft enamel | I13: Epoxy - text | J13: Epoxy - images | K13: Hot stamping - text | L13: Hot stamping - image | M13: Tin stamping | N13: Heat transfer printing - text | O13: Heat transfer printing - image | P13: Embroidery | Q13: Flocking | R13: Heat press printing - text | S13: Heat press printing - image | T13: Digital printing | U13: Debossing | V13: Woven pattern - adhesive patch
B14: Secondary technique - [Metal product customization technique] - [Single technique] - [Custom product] | C14: Laser engraving - text | D14: Laser engraving - images | E14: Mechanical engraving - text | F14: Debossing | G14: Welding | H14: Etching | I14: UV | J14: Silk screen printing - text | K14: Silk screen printing - image | L14: Spray painting | M14: Soft enamel | N14: Epoxy - text | O14: Epoxy - images | P14: Laser cutting - text | Q14: Laser cutting - image | R14: Rhinestone setting | S14: Electroplating
B15: Secondary technique - [Organic material (e.g., acrylic/resin) customization technique] - [Single technique] - [Custom product] | C15: Laser engraving - text | D15: Laser engraving - images | E15: Mechanical engraving - text | F15: Debossing | G15: UV | H15: Silk screen printing - text | I15: Silk screen printing - image | J15: Laser cutting - text | K15: Laser cutting - image | L15: Hand-painted nail art
B16: Secondary technique - [Wood product customization technique] - [Single technique] - [Custom product] | C16: Laser engraving - text | D16: Laser engraving - images | E16: Mechanical engraving - text | F16: Debossing
B17: Update or Add | C17: Update | D17: PartialUpdate | E17: Add
B18: Brand | C18: Must first finish adding the brand in [https://seller.temu.com/brands-property.html], and all available brand names of the store will be displayed here.
A19: Product Detail
B20: 19 - Style - [12155] | C20: Vintage | D20: Boho | E20: Glam | F20: Classic | G20: Contemporary | H20: Traditional | I20: International | J20: Cape Cod | K20: Rustic | L20: French country | M20: Lodge | N20: Mediterranean | O20: Shabby Chic | P20: Southwestern | Q20: Garden | R20: Tropical | S20: Art deco | T20: Modern | U20: Eclectic | V20: Asian | W20: Moroccan | X20: Scandinavian | Y20: Colonial | Z20: English | AA20: French | AB20: Italian | AC20: Mission | AD20: Old World | AE20: Shaker | AF20: Victorian | AG20: Latin | AH20: Chinese | AI20: Japanese | AJ20: Antique | AK20: Baroque | AL20: Coastal | AM20: Industrial | AN20: Tiffany | AO20: Mid-century modern | AP20: Transitional | AQ20: Farmhouse | AR20: Americana | AS20: European | AT20: Nautical | AU20: Italian | AV20: Country rustic
B21: 423 - Holidays - [12155] | C21: Christmas | D21: Halloween | E21: Easter | F21: Hanukkah | G21: Thanksgiving | H21: St. Patrick's Day | I21: Valentine's Day | J21: Ramadan (Eid Al-Fitr) | K21: Father's Day | L21: Mother's Day | M21: Graduation | N21: Juneteenth | O21: 4th of July | P21: Oktoberfest | Q21: Day of the Dead | R21: Diwali | S21: Memorial Day | T21: Saint Nicholas Day | U21: Kwanzaa | V21: Labor Day | W21: Grandparents Day | X21: Earth Day | Y21: Purim | Z21: St. Patrick's Day | AA21: National Freedom Day | AB21: Groundhog Day | AC21: National Wear Red Day | AD21: Palm Sunday | AE21: Lei Day | AF21: Cinco de Mayo | AG21: National Nurses Day | AH21: Eid ul Adha | AI21: French National Day | AJ21: Muharram/Islamic New Year | AK21: National Aviation Day | AL21: National Grandparents Day | AM21: St. Nicholas Day
B22: 127 - Mounting Type - [12155] | C22: Wall hanging | D22: Door mount | E22: Tabletop | F22: Pole Mount | G22: Stand mount
B23: 121 - Material - [12155] | C23: Glass | D23: Suede | E23: Plastic | F23: Wood | G23: Vinyl | H23: Leather | I23: Ceramic | J23: Wicker | K23: Manufactured wood | L23: Aluminum | M23: Stainless Steel | N23: Pewter | O23: Acrylic | P23: Resin | Q23: Rattan | R23: Iron | S23: Porcelain | T23: Bamboo | U23: Crystal | V23: Stone | W23: Abs (acrylonitrile Butadiene Styrene) | X23: Polyethylene | Y23: Polyurethane (pu) | Z23: PET (polyethylene Terephthalate) | AA23: Terracotta | AB23: Melamine | AC23: PC (Polycarbonate) | AD23: PS (polystyrene) | AE23: Tritan | AF23: enamel | AG23: wheat straw | AH23: Plant | AI23: Pampas Grass | AJ23: Log | AK23: Genuine Leather | AL23: Rubber | AM23: PE
B24: 130 - Theme - [12155] | C24: Animals | D24: Military | E24: Flowers | F24: Insects | G24: Plants | H24: Religious | I24: Family | J24: Reptiles | K24: Schools | L24: Seascape | M24: Bird | N24: Heart | O24: Nautical | P24: Pop culture | Q24: Pastoral-themes | R24: Angels | S24: Buildings | T24: Dinosaurs | U24: Gargoyles | V24: Celestial-symbols | W24: Romance | X24: Teddy-bears | Y24: Christian-crosses | Z24: Candy-canes | AA24: Elves | AB24: Santa-claus | AC24: Nativity-theme | AD24: Christmas-nutcrackers | AE24: Snowmen | AF24: Snow-sleds | AG24: Stars | AH24: Trains | AI24: Christmas-stockings | AJ24: Wedding | AK24: Bears | AL24: Christmas-gingerbread-houses | AM24: Cats | AN24: Dogs | AO24: Deer | AP24: Elephants | AQ24: Giraffes | AR24: Foxes | AS24: Primates | AT24: Koalas | AU24: Horses | AV24: Kangaroos | AW24: Rodents | AX24: Rabbits | AY24: Otters | AZ24: Skunks | BA24: Raccoons | BB24: Wolves | BC24: Zebras | BD24: Hippopotamuses | BE24: Rhinoceroses | BF24: Moose | BG24: Elk | BH24: Amphibians | BI24: Carnivals | BJ24: Turtles | BK24: Clowns | BL24: Churches | BM24: Urban | BN24: Retail-shops | BO24: Gourmet-food | BP24: Wine | BQ24: Restaurants | BR24: Landscape | BS24: Vegetables-produce | BT24: Fruit-produce | BU24: Christmas Tree | BV24: Colleges-and-universities | BW24: Inspirational | BX24: Christmas-wreaths | BY24: Christmas-gingerbread-men
B25: 2232 - Whether There Are Feathers - [12155] | C25: Yes | D25: No
B26: 2233 - Feather Material - [Yes] - [12155] | C26: Duck Feather | D26: Goose Feather | E26: Turkey Feathers | F26: Blue Peacock Feather | G26: Artificial Feather | H26: Ostrich Feather | I26: Chicken Feather
B27: 1561 - Power Supply - [12155] | C27: Dry Battery Power | D27: Use Without Electricity | E27: Plug Powered | F27: Solar Charging | G27: USB Powered | H27: Hard-Wired | I27: USB Charging (built-in Battery) | J27: DC Power Supply
B28: 1132 - Operating Voltage - [DC Power Supply] - [12155] | C28: ≤36V
B29: 1132 - Operating Voltage - [Hard-Wired] - [12155] | C29: 110V (included)-240V (included) | D29: 110V | E29: 120V | F29: 130V | G29: 125V
B30: 1132 - Operating Voltage - [Plug Powered] - [12155] | C30: 110V (included)-240V (included) | D30: 110V | E30: 120V | F30: 110V (included)-130V (included) | G30: 130V | H30: 125V | I30: 100V (inclusive)-127V (inclusive) | J30: 110V (inclusive)-127V (inclusive)
B31: 1132 - Operating Voltage - [USB Powered] - [12155] | C31: ≤36V
B32: 1562 - Battery Quantity - [Dry Battery Power] - [12155] | C32: 1 Piece | D32: 2 Pieces | E32: 3 Pieces | F32: 4 Pieces | G32: 5 Pieces | H32: 6 Pieces | I32: 7 Pieces | J32: 8 Pieces
B33: 137 - Battery Type - [Dry Battery Power] - [12155] | C33: 3.6V Rechargeable Li-ion Button Battery | D33: 3V Rechargeable Li-ion Button Battery | E33: Other (non-rechargeable) | F33: 3V Lithium Manganese Button Battery | G33: 1.5V Alkaline Zinc Manganese Button Battery | H33: AA Battery | I33: Button Battery (Diameter≥20mm) | J33: AAA Battery | K33: Button Battery (Diameter＜20mm)
B34: 1563 - Battery Included or Not - [Dry Battery Power] - [12155] | C34: No | D34: Yes
B35: 1485 - Plug Type - [Plug Powered] - [12155] | C35: US Plug
B36: 2147 - Rechargeable Battery - [USB Charging (built-in Battery)] - [12155] | C36: Nickel Battery | D36: Lithium Battery
B37: 2154 - Solar Battery Type - [Solar Charging] - [12155] | C37: Lithium Battery | D37: Nickel Battery
B38: 111 - Batteries Included - [Dry Battery Power] - [12155] | C38: Yes | D38: No
B39: 2028 - Battery Capacity (mAh) - unit - [12155] | C39: MAh
B40: 3673 - Language Type - [12155] | C40: English | D40: German | E40: French | F40: Spanish | G40: Japanese | H40: Korean | I40: Arabic | J40: Portuguese | K40: Italian | L40: Other Languages | M40: No Language | N40: Spanish | O40: Dutch | P40: Polish | Q40: Swedish | R40: Russian | S40: Thai | T40: Malay | U40: Romanian | V40: Greek | W40: Turkish
B41: 7644 - Does It Contain Real Plants? - [12155] | C41: yes | D41: No
A42: Sale Property (At Least One, At Most Two)
B43: Variation Theme - [12155] | C43: Hair Length × Model | D43: Composition × Style | E43: Hair Length × Size | F43: Flavors × Quantity | G43: Size | H43: Quantity × Style | I43: Applicable People × Weight | J43: Color × Model | K43: Applicable People × Material | L43: Capacity × Model | M43: Flavors × Model | N43: Capacity | O43: Model × Quantity | P43: Items | Q43: Material × Style | R43: Model × Size | S43: Applicable People × Model | T43: Applicable People × Size | U43: Color × Material | V43: Capacity × Items | W43: Items × Model | X43: Color | Y43: Color × Style | Z43: Material × Quantity | AA43: Flavors × Weight | AB43: Weight | AC43: Color × Quantity | AD43: Capacity × Hair Length | AE43: Composition × Size | AF43: Applicable People × Color | AG43: Material × Size | AH43: Flavors | AI43: Items × Weight | AJ43: Hair Length × Material | AK43: Hair Length × Quantity | AL43: Applicable People × Flavors | AM43: Flavors × Material | AN43: Capacity × Style | AO43: Applicable People × Quantity | AP43: Quantity × Weight | AQ43: Size × Style | AR43: Flavors × Style | AS43: Applicable People | AT43: Capacity × Weight | AU43: Color × Items | AV43: Capacity × Flavors | AW43: Composition × Hair Length | AX43: Hair Length × Items | AY43: Size × Weight | AZ43: Hair Length × Style | BA43: Quantity × Size | BB43: Color × Flavors | BC43: Style | BD43: Color × Hair Length | BE43: Composition × Weight | BF43: Applicable People × Hair Length | BG43: Hair Length | BH43: Composition | BI43: Applicable People × Capacity | BJ43: Composition × Items | BK43: Items × Quantity | BL43: Flavors × Items | BM43: Flavors × Size | BN43: Quantity | BO43: Material | BP43: Capacity × Color | BQ43: Capacity × Material | BR43: Items × Size | BS43: Capacity × Quantity | BT43: Style × Weight | BU43: Composition × Quantity | BV43: Items × Material | BW43: Capacity × Composition | BX43: Color × Weight | BY43: Color × Size | BZ43: Hair Length × Weight | CA43: Applicable People × Composition | CB43: Material × Weight | CC43: Model × Weight | CD43: Applicable People × Items | CE43: Color × Composition | CF43: Composition × Model | CG43: Model × Style | CH43: Composition × Flavors | CI43: Flavors × Hair Length | CJ43: Items × Style | CK43: Composition × Material | CL43: Model | CM43: Material × Model | CN43: Applicable People × Style | CO43: Capacity × Size
A44: Variations
B45: SKU type | C45: Single set | D45: Multi-piece set | E45: Mixed set of different specifications | F45: Mixed set of different products
B46: Individually packed | C46: No | D46: Yes
B47: Packaging unit | C47: piece | D47: pair | E47: pack
B48: Item unit | C48: piece | D48: pair | E48: pack
B49: Net content unit | C49: oz | D49: lb | E49: kg | F49: g | G49: fl oz | H49: gal | I49: ml | J49: l | K49: m³ | L49: ft | M49: in | N49: m | O49: cm | P49: mm | Q49: sq ft | R49: m² | S49: sq in | T49: mm² | U49: cm² | V49: count
B50: External Product ID Type - [12155] | C50: EAN | D50: UPC | E50: ISBN | F50: GTIN-14
A51: Offer
B52: Shipping Template | C52: Shipping
B53: Handling Time - [Canvas/paper customization technique] - [Combined techniques] - [Custom product] | C53: 1 Day | D53: 2 Days | E53: 3 Days | F53: 4 Days | G53: 5 Days | H53: 6 Days | I53: 7 Days
B54: Handling Time - [Leather/fabric customization technique] - [Combined techniques] - [Custom product] | C54: 1 Day | D54: 2 Days | E54: 3 Days | F54: 4 Days | G54: 5 Days | H54: 6 Days | I54: 7 Days
B55: Handling Time - [Metal product customization technique] - [Combined techniques] - [Custom product] | C55: 1 Day | D55: 2 Days | E55: 3 Days | F55: 4 Days | G55: 5 Days | H55: 6 Days | I55: 7 Days
B56: Handling Time - [Organic material (e.g., acrylic/resin) customization technique] - [Combined techniques] - [Custom product] | C56: 1 Day | D56: 2 Days | E56: 3 Days | F56: 4 Days | G56: 5 Days | H56: 6 Days | I56: 7 Days
B57: Handling Time - [Wood product customization technique] - [Combined techniques] - [Custom product] | C57: 1 Day | D57: 2 Days | E57: 3 Days | F57: 4 Days | G57: 5 Days | H57: 6 Days | I57: 7 Days
B58: Handling Time - [Basic technique] - [Single technique] - [Custom product] | C58: 1 Day | D58: 2 Days | E58: 3 Days
B59: Handling Time - [Canvas/paper customization technique] - [Single technique] - [Custom product] | C59: 1 Day | D59: 2 Days | E59: 3 Days | F59: 4 Days | G59: 5 Days
B60: Handling Time - [Leather/fabric customization technique] - [Single technique] - [Custom product] | C60: 1 Day | D60: 2 Days | E60: 3 Days | F60: 4 Days | G60: 5 Days
B61: Handling Time - [Metal product customization technique] - [Single technique] - [Custom product] | C61: 1 Day | D61: 2 Days | E61: 3 Days | F61: 4 Days | G61: 5 Days
B62: Handling Time - [Organic material (e.g., acrylic/resin) customization technique] - [Single technique] - [Custom product] | C62: 1 Day | D62: 2 Days | E62: 3 Days | F62: 4 Days | G62: 5 Days
B63: Handling Time - [Wood product customization technique] - [Single technique] - [Custom product] | C63: 1 Day | D63: 2 Days | E63: 3 Days | F63: 4 Days | G63: 5 Days
B64: Handling Time - [Custom product] | C64: 1 Day | D64: 2 Days | E64: 3 Days
B65: Handling Time | C65: 1 Day | D65: 2 Days
B66: Handling Time - [Normal product] | C66: 1 Day | D66: 2 Days
B67: Import Designation | C67: Imported | D67: Made in the USA | E67: Made in the USA and Imported | F67: Made in the USA or Imported
B68: Fulfillment Channel | C68: I will ship this item myself
A69: Qualifications
B70: Country/Region of Origin - [12155] | C70: Afghanistan | D70: Albania | E70: Algeria | F70: Andorra | G70: Angola | H70: Anguilla | I70: Antigua and Barbuda | J70: Argentina | K70: Armenia | L70: Aruba | M70: Australia | N70: Austria | O70: Azerbaijan | P70: Bahamas | Q70: Bahrain | R70: Bangladesh | S70: Barbados | T70: Belarus | U70: Belgium | V70: Belize | W70: Benin | X70: Bermuda | Y70: Bhutan | Z70: Bolivia | AA70: Bosnia and Herzegovina | AB70: Botswana | AC70: Bouvet Island | AD70: Brazil | AE70: British Indian Ocean Territory | AF70: Brunei Darussalam | AG70: Bulgaria | AH70: Burkina Faso | AI70: Burundi | AJ70: Cambodia | AK70: Cameroon | AL70: Canada | AM70: Cape Verde | AN70: Cayman Islands | AO70: Central African Republic | AP70: Chad | AQ70: Chile | AR70: Mainland China | AS70: Christmas Island | AT70: Colombia | AU70: Comoros | AV70: Congo | AW70: Cook Islands | AX70: Costa Rica | AY70: Croatia | AZ70: Cuba | BA70: Cyprus | BB70: Czech Republic | BC70: Denmark | BD70: Djibouti | BE70: Dominica | BF70: Dominican Republic | BG70: East Timor | BH70: Ecuador | BI70: Egypt | BJ70: El Salvador | BK70: Equatorial Guinea | BL70: Eritrea | BM70: Estonia | BN70: Ethiopia | BO70: Faroe Islands | BP70: Fiji | BQ70: Finland | BR70: France | BS70: French Guiana | BT70: French Polynesia | BU70: French Southern Territories | BV70: Gabon | BW70: Gambia | BX70: Georgia | BY70: Germany | BZ70: Ghana | CA70: Gibraltar | CB70: Greece | CC70: Greenland | CD70: Grenada | CE70: Guadeloupe | CF70: Guam | CG70: Guatemala | CH70: Guinea | CI70: Guinea-Bissau | CJ70: Guyana | CK70: Haiti | CL70: Honduras | CM70: HK | CN70: Hungary | CO70: Iceland | CP70: India | CQ70: Indonesia | CR70: Iran | CS70: Iraq | CT70: Ireland | CU70: Israel | CV70: Italy | CW70: Jamaica | CX70: Japan | CY70: Jordan | CZ70: Kazakhstan | DA70: Kenya | DB70: Kiribati | DC70: Kosovo | DD70: Kuwait | DE70: Kyrgyzstan | DF70: Lao People's Democratic Republic | DG70: Latvia | DH70: Lebanon | DI70: Lesotho | DJ70: Liberia | DK70: Liechtenstein | DL70: Lithuania | DM70: Luxembourg | DN70: MO | DO70: Madagascar | DP70: Malawi | DQ70: Malaysia | DR70: Maldives | DS70: Mali | DT70: Malta | DU70: Marshall Islands | DV70: Martinique | DW70: Mauritania | DX70: Mauritius | DY70: Mayotte | DZ70: Mexico | EA70: Micronesia | EB70: Moldova | EC70: Monaco | ED70: Mongolia | EE70: Montenegro | EF70: Montserrat | EG70: Morocco | EH70: Mozambique | EI70: Myanmar | EJ70: Namibia | EK70: Nauru | EL70: Nepal | EM70: Netherlands | EN70: Netherlands Antilles | EO70: New Caledonia | EP70: New Zealand | EQ70: Nicaragua | ER70: Niger | ES70: Nigeria | ET70: Niue | EU70: Norfolk Island | EV70: North Korea | EW70: North Macedonia | EX70: Northern Mariana Islands | EY70: Norway | EZ70: Oman | FA70: Pakistan | FB70: Palau | FC70: Palestine | FD70: Panama | FE70: Papua New Guinea | FF70: Paraguay | FG70: Peru | FH70: Philippines | FI70: Pitcairn | FJ70: Poland | FK70: Portugal | FL70: Puerto Rico | FM70: Qatar | FN70: Republic of Korea | FO70: Reunion | FP70: Romania | FQ70: Russian Federation | FR70: Rwanda | FS70: Saint Lucia | FT70: Samoa | FU70: San Marino | FV70: Sao Tome and Principe | FW70: Saudi Arabia | FX70: Senegal | FY70: Serbia | FZ70: Seychelles | GA70: Sierra Leone | GB70: Singapore | GC70: Slovakia (Slovak Republic) | GD70: Slovenia | GE70: Solomon Islands | GF70: Somalia | GG70: South Africa | GH70: Spain | GI70: Sri Lanka | GJ70: Sudan | GK70: Suriname | GL70: Swaziland | GM70: Sweden | GN70: Switzerland | GO70: Syrian Arab Republic | GP70: TW | GQ70: Tajikistan | GR70: Tanzania | GS70: Thailand | GT70: Togo | GU70: Tokelau | GV70: Tonga | GW70: Trinidad and Tobago | GX70: Tunisia | GY70: Türkiye | GZ70: Turkmenistan | HA70: Turks and Caicos Islands | HB70: Tuvalu | HC70: Uganda | HD70: Ukraine | HE70: United Arab Emirates | HF70: United Kingdom | HG70: United States | HH70: Uruguay | HI70: Uzbekistan | HJ70: Vanuatu | HK70: Vatican City State (Holy See) | HL70: Venezuela | HM70: Vietnam | HN70: Virgin Islands (British) | HO70: Virgin Islands (U.S.) | HP70: Wallis And Futuna Islands | HQ70: Western Sahara | HR70: Yemen | HS70: Yugoslavia | HT70: Zambia | HU70: Zimbabwe
B71: Province of Origin - [Mainland China] | C71: Beijing | D71: Shanghai | E71: Tianjin | F71: Chongqing | G71: Hebei | H71: Shanxi | I71: Liaoning | J71: Jilin | K71: Heilongjiang | L71: Jiangsu | M71: Zhejiang | N71: Anhui | O71: Fujian | P71: Jiangxi | Q71: Shandong | R71: Henan | S71: Hubei | T71: Hunan | U71: Guangdong | V71: Hainan | W71: Sichuan | X71: Guizhou | Y71: Yunnan | Z71: Shaanxi | AA71: Gansu | AB71: Qinghai | AC71: Inner Mongolia | AD71: Guangxi | AE71: Xizang | AF71: Ningxia | AG71: Xinjiang
B72: California Proposition 65 Warning Type - [12155] | C72: Chemical | D72: Food | E72: Furniture | F72: Alcoholic Beverage | G72: Passenger or Off Road Vehicle | H72: On Product Cancer | I72: On Product Combined Cancer Reproductive | J72: On Product Reproductive | K72: No Warning Applicable | L72: Diesel Engines
